{
    "PE_0000_0000": "Layer ID: 40\n\nGrid Row ID: 0\n\nGrid Col ID: 0\n\nCompute Cycles: 37379.0\n\nIFMAP DRAM Reads: 13200.0\n\nFilter DRAM Reads: 21120.0\n\nOFMAP DRAM Writes: 1000.0\n\nIFMAP DRAM Start Cycle: -15729.0\n\nFilter DRAM Start Cycle: -15729.0\n\nOFMAP DRAM Start Cycle: 37379.0\n\nIFMAP DRAM End Cycle: -1.0\n\nFilter DRAM End Cycle: -1.0\n\nOFMAP DRAM End Cycle: 37628.0\n\nTotal Compute Cycles: 37379\n\nTotal Stall Cycles: 0\n\nIFMAP SRAM Access Range: (1.0, 37374.0)\n\nFilter SRAM Access Range: (1.0, 37377.0)\n\nOFMAP SRAM Access Range: (527.0, 37379.0)\n\nIFMAP DRAM Access Range: (-15729.0, -1.0)\n\nFilter DRAM Access Range: (-15729.0, -1.0)\n\nOFMAP DRAM Access Range: (37379.0, 37628.0)\n\nIFMAP SRAM Access Count: 13200\n\nFilter SRAM Access Count: 21120\n\nOFMAP SRAM Access Count: 1000\n\nIFMAP DRAM Access Count: 13200\n\nFilter DRAM Access Count: 21120\n\nOFMAP DRAM Access Count: 1000\n\nIFMAP Buffer Size (bytes): 6291456\n\nFilter Buffer Size (bytes): 6291456\n\nOFMAP Buffer Size (bytes): 2097152\n\nIFMAP Buffer Utilization (%): 0.209808349609375\n\nFilter Buffer Utilization (%): 0.335693359375\n\nOFMAP Buffer Utilization (%): 0.0476837158203125\n",
    "PE_0000_0001": "Layer ID: 40\n\nGrid Row ID: 0\n\nGrid Col ID: 1\n\nCompute Cycles: 37379.0\n\nIFMAP DRAM Reads: 13200.0\n\nFilter DRAM Reads: 21120.0\n\nOFMAP DRAM Writes: 1000.0\n\nIFMAP DRAM Start Cycle: -15729.0\n\nFilter DRAM Start Cycle: -15729.0\n\nOFMAP DRAM Start Cycle: 37379.0\n\nIFMAP DRAM End Cycle: -1.0\n\nFilter DRAM End Cycle: -1.0\n\nOFMAP DRAM End Cycle: 37628.0\n\nTotal Compute Cycles: 37379\n\nTotal Stall Cycles: 0\n\nIFMAP SRAM Access Range: (1.0, 37374.0)\n\nFilter SRAM Access Range: (1.0, 37377.0)\n\nOFMAP SRAM Access Range: (527.0, 37379.0)\n\nIFMAP DRAM Access Range: (-15729.0, -1.0)\n\nFilter DRAM Access Range: (-15729.0, -1.0)\n\nOFMAP DRAM Access Range: (37379.0, 37628.0)\n\nIFMAP SRAM Access Count: 13200\n\nFilter SRAM Access Count: 21120\n\nOFMAP SRAM Access Count: 1000\n\nIFMAP DRAM Access Count: 13200\n\nFilter DRAM Access Count: 21120\n\nOFMAP DRAM Access Count: 1000\n\nIFMAP Buffer Size (bytes): 6291456\n\nFilter Buffer Size (bytes): 6291456\n\nOFMAP Buffer Size (bytes): 2097152\n\nIFMAP Buffer Utilization (%): 0.209808349609375\n\nFilter Buffer Utilization (%): 0.335693359375\n\nOFMAP Buffer Utilization (%): 0.0476837158203125\n",
    "PE_0000_0002": "Layer ID: 40\n\nGrid Row ID: 0\n\nGrid Col ID: 2\n\nCompute Cycles: 37379.0\n\nIFMAP DRAM Reads: 13200.0\n\nFilter DRAM Reads: 21120.0\n\nOFMAP DRAM Writes: 1000.0\n\nIFMAP DRAM Start Cycle: -15729.0\n\nFilter DRAM Start Cycle: -15729.0\n\nOFMAP DRAM Start Cycle: 37379.0\n\nIFMAP DRAM End Cycle: -1.0\n\nFilter DRAM End Cycle: -1.0\n\nOFMAP DRAM End Cycle: 37628.0\n\nTotal Compute Cycles: 37379\n\nTotal Stall Cycles: 0\n\nIFMAP SRAM Access Range: (1.0, 37374.0)\n\nFilter SRAM Access Range: (1.0, 37377.0)\n\nOFMAP SRAM Access Range: (527.0, 37379.0)\n\nIFMAP DRAM Access Range: (-15729.0, -1.0)\n\nFilter DRAM Access Range: (-15729.0, -1.0)\n\nOFMAP DRAM Access Range: (37379.0, 37628.0)\n\nIFMAP SRAM Access Count: 13200\n\nFilter SRAM Access Count: 21120\n\nOFMAP SRAM Access Count: 1000\n\nIFMAP DRAM Access Count: 13200\n\nFilter DRAM Access Count: 21120\n\nOFMAP DRAM Access Count: 1000\n\nIFMAP Buffer Size (bytes): 6291456\n\nFilter Buffer Size (bytes): 6291456\n\nOFMAP Buffer Size (bytes): 2097152\n\nIFMAP Buffer Utilization (%): 0.209808349609375\n\nFilter Buffer Utilization (%): 0.335693359375\n\nOFMAP Buffer Utilization (%): 0.0476837158203125\n",
    "PE_0000_0003": "Layer ID: 40\n\nGrid Row ID: 0\n\nGrid Col ID: 3\n\nCompute Cycles: 37379.0\n\nIFMAP DRAM Reads: 13200.0\n\nFilter DRAM Reads: 20592.0\n\nOFMAP DRAM Writes: 975.0\n\nIFMAP DRAM Start Cycle: -15729.0\n\nFilter DRAM Start Cycle: -15729.0\n\nOFMAP DRAM Start Cycle: 37379.0\n\nIFMAP DRAM End Cycle: -1.0\n\nFilter DRAM End Cycle: -1.0\n\nOFMAP DRAM End Cycle: 37622.0\n\nTotal Compute Cycles: 37379\n\nTotal Stall Cycles: 0\n\nIFMAP SRAM Access Range: (1.0, 37374.0)\n\nFilter SRAM Access Range: (1.0, 37376.0)\n\nOFMAP SRAM Access Range: (527.0, 37378.0)\n\nIFMAP DRAM Access Range: (-15729.0, -1.0)\n\nFilter DRAM Access Range: (-15729.0, -1.0)\n\nOFMAP DRAM Access Range: (37379.0, 37622.0)\n\nIFMAP SRAM Access Count: 13200\n\nFilter SRAM Access Count: 20592\n\nOFMAP SRAM Access Count: 975\n\nIFMAP DRAM Access Count: 13200\n\nFilter DRAM Access Count: 20592\n\nOFMAP DRAM Access Count: 975\n\nIFMAP Buffer Size (bytes): 6291456\n\nFilter Buffer Size (bytes): 6291456\n\nOFMAP Buffer Size (bytes): 2097152\n\nIFMAP Buffer Utilization (%): 0.209808349609375\n\nFilter Buffer Utilization (%): 0.327301025390625\n\nOFMAP Buffer Utilization (%): 0.04649162292480469\n",
    "PE_0001_0000": "Layer ID: 40\n\nGrid Row ID: 1\n\nGrid Col ID: 0\n\nCompute Cycles: 37379.0\n\nIFMAP DRAM Reads: 13200.0\n\nFilter DRAM Reads: 21120.0\n\nOFMAP DRAM Writes: 1000.0\n\nIFMAP DRAM Start Cycle: -15729.0\n\nFilter DRAM Start Cycle: -15729.0\n\nOFMAP DRAM Start Cycle: 37379.0\n\nIFMAP DRAM End Cycle: -1.0\n\nFilter DRAM End Cycle: -1.0\n\nOFMAP DRAM End Cycle: 37628.0\n\nTotal Compute Cycles: 37379\n\nTotal Stall Cycles: 0\n\nIFMAP SRAM Access Range: (1.0, 37374.0)\n\nFilter SRAM Access Range: (1.0, 37377.0)\n\nOFMAP SRAM Access Range: (527.0, 37379.0)\n\nIFMAP DRAM Access Range: (-15729.0, -1.0)\n\nFilter DRAM Access Range: (-15729.0, -1.0)\n\nOFMAP DRAM Access Range: (37379.0, 37628.0)\n\nIFMAP SRAM Access Count: 13200\n\nFilter SRAM Access Count: 21120\n\nOFMAP SRAM Access Count: 1000\n\nIFMAP DRAM Access Count: 13200\n\nFilter DRAM Access Count: 21120\n\nOFMAP DRAM Access Count: 1000\n\nIFMAP Buffer Size (bytes): 6291456\n\nFilter Buffer Size (bytes): 6291456\n\nOFMAP Buffer Size (bytes): 2097152\n\nIFMAP Buffer Utilization (%): 0.209808349609375\n\nFilter Buffer Utilization (%): 0.335693359375\n\nOFMAP Buffer Utilization (%): 0.0476837158203125\n",
    "PE_0001_0001": "Layer ID: 40\n\nGrid Row ID: 1\n\nGrid Col ID: 1\n\nCompute Cycles: 37379.0\n\nIFMAP DRAM Reads: 13200.0\n\nFilter DRAM Reads: 21120.0\n\nOFMAP DRAM Writes: 1000.0\n\nIFMAP DRAM Start Cycle: -15729.0\n\nFilter DRAM Start Cycle: -15729.0\n\nOFMAP DRAM Start Cycle: 37379.0\n\nIFMAP DRAM End Cycle: -1.0\n\nFilter DRAM End Cycle: -1.0\n\nOFMAP DRAM End Cycle: 37628.0\n\nTotal Compute Cycles: 37379\n\nTotal Stall Cycles: 0\n\nIFMAP SRAM Access Range: (1.0, 37374.0)\n\nFilter SRAM Access Range: (1.0, 37377.0)\n\nOFMAP SRAM Access Range: (527.0, 37379.0)\n\nIFMAP DRAM Access Range: (-15729.0, -1.0)\n\nFilter DRAM Access Range: (-15729.0, -1.0)\n\nOFMAP DRAM Access Range: (37379.0, 37628.0)\n\nIFMAP SRAM Access Count: 13200\n\nFilter SRAM Access Count: 21120\n\nOFMAP SRAM Access Count: 1000\n\nIFMAP DRAM Access Count: 13200\n\nFilter DRAM Access Count: 21120\n\nOFMAP DRAM Access Count: 1000\n\nIFMAP Buffer Size (bytes): 6291456\n\nFilter Buffer Size (bytes): 6291456\n\nOFMAP Buffer Size (bytes): 2097152\n\nIFMAP Buffer Utilization (%): 0.209808349609375\n\nFilter Buffer Utilization (%): 0.335693359375\n\nOFMAP Buffer Utilization (%): 0.0476837158203125\n",
    "PE_0001_0002": "Layer ID: 40\n\nGrid Row ID: 1\n\nGrid Col ID: 2\n\nCompute Cycles: 37379.0\n\nIFMAP DRAM Reads: 13200.0\n\nFilter DRAM Reads: 21120.0\n\nOFMAP DRAM Writes: 1000.0\n\nIFMAP DRAM Start Cycle: -15729.0\n\nFilter DRAM Start Cycle: -15729.0\n\nOFMAP DRAM Start Cycle: 37379.0\n\nIFMAP DRAM End Cycle: -1.0\n\nFilter DRAM End Cycle: -1.0\n\nOFMAP DRAM End Cycle: 37628.0\n\nTotal Compute Cycles: 37379\n\nTotal Stall Cycles: 0\n\nIFMAP SRAM Access Range: (1.0, 37374.0)\n\nFilter SRAM Access Range: (1.0, 37377.0)\n\nOFMAP SRAM Access Range: (527.0, 37379.0)\n\nIFMAP DRAM Access Range: (-15729.0, -1.0)\n\nFilter DRAM Access Range: (-15729.0, -1.0)\n\nOFMAP DRAM Access Range: (37379.0, 37628.0)\n\nIFMAP SRAM Access Count: 13200\n\nFilter SRAM Access Count: 21120\n\nOFMAP SRAM Access Count: 1000\n\nIFMAP DRAM Access Count: 13200\n\nFilter DRAM Access Count: 21120\n\nOFMAP DRAM Access Count: 1000\n\nIFMAP Buffer Size (bytes): 6291456\n\nFilter Buffer Size (bytes): 6291456\n\nOFMAP Buffer Size (bytes): 2097152\n\nIFMAP Buffer Utilization (%): 0.209808349609375\n\nFilter Buffer Utilization (%): 0.335693359375\n\nOFMAP Buffer Utilization (%): 0.0476837158203125\n",
    "PE_0001_0003": "Layer ID: 40\n\nGrid Row ID: 1\n\nGrid Col ID: 3\n\nCompute Cycles: 37379.0\n\nIFMAP DRAM Reads: 13200.0\n\nFilter DRAM Reads: 20592.0\n\nOFMAP DRAM Writes: 975.0\n\nIFMAP DRAM Start Cycle: -15729.0\n\nFilter DRAM Start Cycle: -15729.0\n\nOFMAP DRAM Start Cycle: 37379.0\n\nIFMAP DRAM End Cycle: -1.0\n\nFilter DRAM End Cycle: -1.0\n\nOFMAP DRAM End Cycle: 37622.0\n\nTotal Compute Cycles: 37379\n\nTotal Stall Cycles: 0\n\nIFMAP SRAM Access Range: (1.0, 37374.0)\n\nFilter SRAM Access Range: (1.0, 37376.0)\n\nOFMAP SRAM Access Range: (527.0, 37378.0)\n\nIFMAP DRAM Access Range: (-15729.0, -1.0)\n\nFilter DRAM Access Range: (-15729.0, -1.0)\n\nOFMAP DRAM Access Range: (37379.0, 37622.0)\n\nIFMAP SRAM Access Count: 13200\n\nFilter SRAM Access Count: 20592\n\nOFMAP SRAM Access Count: 975\n\nIFMAP DRAM Access Count: 13200\n\nFilter DRAM Access Count: 20592\n\nOFMAP DRAM Access Count: 975\n\nIFMAP Buffer Size (bytes): 6291456\n\nFilter Buffer Size (bytes): 6291456\n\nOFMAP Buffer Size (bytes): 2097152\n\nIFMAP Buffer Utilization (%): 0.209808349609375\n\nFilter Buffer Utilization (%): 0.327301025390625\n\nOFMAP Buffer Utilization (%): 0.04649162292480469\n",
    "PE_0002_0000": "Layer ID: 40\n\nGrid Row ID: 2\n\nGrid Col ID: 0\n\nCompute Cycles: 37379.0\n\nIFMAP DRAM Reads: 13200.0\n\nFilter DRAM Reads: 21120.0\n\nOFMAP DRAM Writes: 1000.0\n\nIFMAP DRAM Start Cycle: -15729.0\n\nFilter DRAM Start Cycle: -15729.0\n\nOFMAP DRAM Start Cycle: 37379.0\n\nIFMAP DRAM End Cycle: -1.0\n\nFilter DRAM End Cycle: -1.0\n\nOFMAP DRAM End Cycle: 37628.0\n\nTotal Compute Cycles: 37379\n\nTotal Stall Cycles: 0\n\nIFMAP SRAM Access Range: (1.0, 37374.0)\n\nFilter SRAM Access Range: (1.0, 37377.0)\n\nOFMAP SRAM Access Range: (527.0, 37379.0)\n\nIFMAP DRAM Access Range: (-15729.0, -1.0)\n\nFilter DRAM Access Range: (-15729.0, -1.0)\n\nOFMAP DRAM Access Range: (37379.0, 37628.0)\n\nIFMAP SRAM Access Count: 13200\n\nFilter SRAM Access Count: 21120\n\nOFMAP SRAM Access Count: 1000\n\nIFMAP DRAM Access Count: 13200\n\nFilter DRAM Access Count: 21120\n\nOFMAP DRAM Access Count: 1000\n\nIFMAP Buffer Size (bytes): 6291456\n\nFilter Buffer Size (bytes): 6291456\n\nOFMAP Buffer Size (bytes): 2097152\n\nIFMAP Buffer Utilization (%): 0.209808349609375\n\nFilter Buffer Utilization (%): 0.335693359375\n\nOFMAP Buffer Utilization (%): 0.0476837158203125\n",
    "PE_0002_0001": "Layer ID: 40\n\nGrid Row ID: 2\n\nGrid Col ID: 1\n\nCompute Cycles: 37379.0\n\nIFMAP DRAM Reads: 13200.0\n\nFilter DRAM Reads: 21120.0\n\nOFMAP DRAM Writes: 1000.0\n\nIFMAP DRAM Start Cycle: -15729.0\n\nFilter DRAM Start Cycle: -15729.0\n\nOFMAP DRAM Start Cycle: 37379.0\n\nIFMAP DRAM End Cycle: -1.0\n\nFilter DRAM End Cycle: -1.0\n\nOFMAP DRAM End Cycle: 37628.0\n\nTotal Compute Cycles: 37379\n\nTotal Stall Cycles: 0\n\nIFMAP SRAM Access Range: (1.0, 37374.0)\n\nFilter SRAM Access Range: (1.0, 37377.0)\n\nOFMAP SRAM Access Range: (527.0, 37379.0)\n\nIFMAP DRAM Access Range: (-15729.0, -1.0)\n\nFilter DRAM Access Range: (-15729.0, -1.0)\n\nOFMAP DRAM Access Range: (37379.0, 37628.0)\n\nIFMAP SRAM Access Count: 13200\n\nFilter SRAM Access Count: 21120\n\nOFMAP SRAM Access Count: 1000\n\nIFMAP DRAM Access Count: 13200\n\nFilter DRAM Access Count: 21120\n\nOFMAP DRAM Access Count: 1000\n\nIFMAP Buffer Size (bytes): 6291456\n\nFilter Buffer Size (bytes): 6291456\n\nOFMAP Buffer Size (bytes): 2097152\n\nIFMAP Buffer Utilization (%): 0.209808349609375\n\nFilter Buffer Utilization (%): 0.335693359375\n\nOFMAP Buffer Utilization (%): 0.0476837158203125\n",
    "PE_0002_0002": "Layer ID: 40\n\nGrid Row ID: 2\n\nGrid Col ID: 2\n\nCompute Cycles: 37379.0\n\nIFMAP DRAM Reads: 13200.0\n\nFilter DRAM Reads: 21120.0\n\nOFMAP DRAM Writes: 1000.0\n\nIFMAP DRAM Start Cycle: -15729.0\n\nFilter DRAM Start Cycle: -15729.0\n\nOFMAP DRAM Start Cycle: 37379.0\n\nIFMAP DRAM End Cycle: -1.0\n\nFilter DRAM End Cycle: -1.0\n\nOFMAP DRAM End Cycle: 37628.0\n\nTotal Compute Cycles: 37379\n\nTotal Stall Cycles: 0\n\nIFMAP SRAM Access Range: (1.0, 37374.0)\n\nFilter SRAM Access Range: (1.0, 37377.0)\n\nOFMAP SRAM Access Range: (527.0, 37379.0)\n\nIFMAP DRAM Access Range: (-15729.0, -1.0)\n\nFilter DRAM Access Range: (-15729.0, -1.0)\n\nOFMAP DRAM Access Range: (37379.0, 37628.0)\n\nIFMAP SRAM Access Count: 13200\n\nFilter SRAM Access Count: 21120\n\nOFMAP SRAM Access Count: 1000\n\nIFMAP DRAM Access Count: 13200\n\nFilter DRAM Access Count: 21120\n\nOFMAP DRAM Access Count: 1000\n\nIFMAP Buffer Size (bytes): 6291456\n\nFilter Buffer Size (bytes): 6291456\n\nOFMAP Buffer Size (bytes): 2097152\n\nIFMAP Buffer Utilization (%): 0.209808349609375\n\nFilter Buffer Utilization (%): 0.335693359375\n\nOFMAP Buffer Utilization (%): 0.0476837158203125\n",
    "PE_0002_0003": "Layer ID: 40\n\nGrid Row ID: 2\n\nGrid Col ID: 3\n\nCompute Cycles: 37379.0\n\nIFMAP DRAM Reads: 13200.0\n\nFilter DRAM Reads: 20592.0\n\nOFMAP DRAM Writes: 975.0\n\nIFMAP DRAM Start Cycle: -15729.0\n\nFilter DRAM Start Cycle: -15729.0\n\nOFMAP DRAM Start Cycle: 37379.0\n\nIFMAP DRAM End Cycle: -1.0\n\nFilter DRAM End Cycle: -1.0\n\nOFMAP DRAM End Cycle: 37622.0\n\nTotal Compute Cycles: 37379\n\nTotal Stall Cycles: 0\n\nIFMAP SRAM Access Range: (1.0, 37374.0)\n\nFilter SRAM Access Range: (1.0, 37376.0)\n\nOFMAP SRAM Access Range: (527.0, 37378.0)\n\nIFMAP DRAM Access Range: (-15729.0, -1.0)\n\nFilter DRAM Access Range: (-15729.0, -1.0)\n\nOFMAP DRAM Access Range: (37379.0, 37622.0)\n\nIFMAP SRAM Access Count: 13200\n\nFilter SRAM Access Count: 20592\n\nOFMAP SRAM Access Count: 975\n\nIFMAP DRAM Access Count: 13200\n\nFilter DRAM Access Count: 20592\n\nOFMAP DRAM Access Count: 975\n\nIFMAP Buffer Size (bytes): 6291456\n\nFilter Buffer Size (bytes): 6291456\n\nOFMAP Buffer Size (bytes): 2097152\n\nIFMAP Buffer Utilization (%): 0.209808349609375\n\nFilter Buffer Utilization (%): 0.327301025390625\n\nOFMAP Buffer Utilization (%): 0.04649162292480469\n",
    "PE_0003_0000": "Layer ID: 40\n\nGrid Row ID: 3\n\nGrid Col ID: 0\n\nCompute Cycles: 37379.0\n\nIFMAP DRAM Reads: 13200.0\n\nFilter DRAM Reads: 21120.0\n\nOFMAP DRAM Writes: 1000.0\n\nIFMAP DRAM Start Cycle: -15729.0\n\nFilter DRAM Start Cycle: -15729.0\n\nOFMAP DRAM Start Cycle: 37379.0\n\nIFMAP DRAM End Cycle: -1.0\n\nFilter DRAM End Cycle: -1.0\n\nOFMAP DRAM End Cycle: 37628.0\n\nTotal Compute Cycles: 37379\n\nTotal Stall Cycles: 0\n\nIFMAP SRAM Access Range: (1.0, 37374.0)\n\nFilter SRAM Access Range: (1.0, 37377.0)\n\nOFMAP SRAM Access Range: (527.0, 37379.0)\n\nIFMAP DRAM Access Range: (-15729.0, -1.0)\n\nFilter DRAM Access Range: (-15729.0, -1.0)\n\nOFMAP DRAM Access Range: (37379.0, 37628.0)\n\nIFMAP SRAM Access Count: 13200\n\nFilter SRAM Access Count: 21120\n\nOFMAP SRAM Access Count: 1000\n\nIFMAP DRAM Access Count: 13200\n\nFilter DRAM Access Count: 21120\n\nOFMAP DRAM Access Count: 1000\n\nIFMAP Buffer Size (bytes): 6291456\n\nFilter Buffer Size (bytes): 6291456\n\nOFMAP Buffer Size (bytes): 2097152\n\nIFMAP Buffer Utilization (%): 0.209808349609375\n\nFilter Buffer Utilization (%): 0.335693359375\n\nOFMAP Buffer Utilization (%): 0.0476837158203125\n",
    "PE_0003_0001": "Layer ID: 40\n\nGrid Row ID: 3\n\nGrid Col ID: 1\n\nCompute Cycles: 37379.0\n\nIFMAP DRAM Reads: 13200.0\n\nFilter DRAM Reads: 21120.0\n\nOFMAP DRAM Writes: 1000.0\n\nIFMAP DRAM Start Cycle: -15729.0\n\nFilter DRAM Start Cycle: -15729.0\n\nOFMAP DRAM Start Cycle: 37379.0\n\nIFMAP DRAM End Cycle: -1.0\n\nFilter DRAM End Cycle: -1.0\n\nOFMAP DRAM End Cycle: 37628.0\n\nTotal Compute Cycles: 37379\n\nTotal Stall Cycles: 0\n\nIFMAP SRAM Access Range: (1.0, 37374.0)\n\nFilter SRAM Access Range: (1.0, 37377.0)\n\nOFMAP SRAM Access Range: (527.0, 37379.0)\n\nIFMAP DRAM Access Range: (-15729.0, -1.0)\n\nFilter DRAM Access Range: (-15729.0, -1.0)\n\nOFMAP DRAM Access Range: (37379.0, 37628.0)\n\nIFMAP SRAM Access Count: 13200\n\nFilter SRAM Access Count: 21120\n\nOFMAP SRAM Access Count: 1000\n\nIFMAP DRAM Access Count: 13200\n\nFilter DRAM Access Count: 21120\n\nOFMAP DRAM Access Count: 1000\n\nIFMAP Buffer Size (bytes): 6291456\n\nFilter Buffer Size (bytes): 6291456\n\nOFMAP Buffer Size (bytes): 2097152\n\nIFMAP Buffer Utilization (%): 0.209808349609375\n\nFilter Buffer Utilization (%): 0.335693359375\n\nOFMAP Buffer Utilization (%): 0.0476837158203125\n",
    "PE_0003_0002": "Layer ID: 40\n\nGrid Row ID: 3\n\nGrid Col ID: 2\n\nCompute Cycles: 37379.0\n\nIFMAP DRAM Reads: 13200.0\n\nFilter DRAM Reads: 21120.0\n\nOFMAP DRAM Writes: 1000.0\n\nIFMAP DRAM Start Cycle: -15729.0\n\nFilter DRAM Start Cycle: -15729.0\n\nOFMAP DRAM Start Cycle: 37379.0\n\nIFMAP DRAM End Cycle: -1.0\n\nFilter DRAM End Cycle: -1.0\n\nOFMAP DRAM End Cycle: 37628.0\n\nTotal Compute Cycles: 37379\n\nTotal Stall Cycles: 0\n\nIFMAP SRAM Access Range: (1.0, 37374.0)\n\nFilter SRAM Access Range: (1.0, 37377.0)\n\nOFMAP SRAM Access Range: (527.0, 37379.0)\n\nIFMAP DRAM Access Range: (-15729.0, -1.0)\n\nFilter DRAM Access Range: (-15729.0, -1.0)\n\nOFMAP DRAM Access Range: (37379.0, 37628.0)\n\nIFMAP SRAM Access Count: 13200\n\nFilter SRAM Access Count: 21120\n\nOFMAP SRAM Access Count: 1000\n\nIFMAP DRAM Access Count: 13200\n\nFilter DRAM Access Count: 21120\n\nOFMAP DRAM Access Count: 1000\n\nIFMAP Buffer Size (bytes): 6291456\n\nFilter Buffer Size (bytes): 6291456\n\nOFMAP Buffer Size (bytes): 2097152\n\nIFMAP Buffer Utilization (%): 0.209808349609375\n\nFilter Buffer Utilization (%): 0.335693359375\n\nOFMAP Buffer Utilization (%): 0.0476837158203125\n",
    "PE_0003_0003": "Layer ID: 40\n\nGrid Row ID: 3\n\nGrid Col ID: 3\n\nCompute Cycles: 37379.0\n\nIFMAP DRAM Reads: 13200.0\n\nFilter DRAM Reads: 20592.0\n\nOFMAP DRAM Writes: 975.0\n\nIFMAP DRAM Start Cycle: -15729.0\n\nFilter DRAM Start Cycle: -15729.0\n\nOFMAP DRAM Start Cycle: 37379.0\n\nIFMAP DRAM End Cycle: -1.0\n\nFilter DRAM End Cycle: -1.0\n\nOFMAP DRAM End Cycle: 37622.0\n\nTotal Compute Cycles: 37379\n\nTotal Stall Cycles: 0\n\nIFMAP SRAM Access Range: (1.0, 37374.0)\n\nFilter SRAM Access Range: (1.0, 37376.0)\n\nOFMAP SRAM Access Range: (527.0, 37378.0)\n\nIFMAP DRAM Access Range: (-15729.0, -1.0)\n\nFilter DRAM Access Range: (-15729.0, -1.0)\n\nOFMAP DRAM Access Range: (37379.0, 37622.0)\n\nIFMAP SRAM Access Count: 13200\n\nFilter SRAM Access Count: 20592\n\nOFMAP SRAM Access Count: 975\n\nIFMAP DRAM Access Count: 13200\n\nFilter DRAM Access Count: 20592\n\nOFMAP DRAM Access Count: 975\n\nIFMAP Buffer Size (bytes): 6291456\n\nFilter Buffer Size (bytes): 6291456\n\nOFMAP Buffer Size (bytes): 2097152\n\nIFMAP Buffer Utilization (%): 0.209808349609375\n\nFilter Buffer Utilization (%): 0.327301025390625\n\nOFMAP Buffer Utilization (%): 0.04649162292480469\n",
    "PE_0004_0000": "Layer ID: 40\n\nGrid Row ID: 4\n\nGrid Col ID: 0\n\nCompute Cycles: 37379.0\n\nIFMAP DRAM Reads: 13200.0\n\nFilter DRAM Reads: 21120.0\n\nOFMAP DRAM Writes: 1000.0\n\nIFMAP DRAM Start Cycle: -15729.0\n\nFilter DRAM Start Cycle: -15729.0\n\nOFMAP DRAM Start Cycle: 37379.0\n\nIFMAP DRAM End Cycle: -1.0\n\nFilter DRAM End Cycle: -1.0\n\nOFMAP DRAM End Cycle: 37628.0\n\nTotal Compute Cycles: 37379\n\nTotal Stall Cycles: 0\n\nIFMAP SRAM Access Range: (1.0, 37374.0)\n\nFilter SRAM Access Range: (1.0, 37377.0)\n\nOFMAP SRAM Access Range: (527.0, 37379.0)\n\nIFMAP DRAM Access Range: (-15729.0, -1.0)\n\nFilter DRAM Access Range: (-15729.0, -1.0)\n\nOFMAP DRAM Access Range: (37379.0, 37628.0)\n\nIFMAP SRAM Access Count: 13200\n\nFilter SRAM Access Count: 21120\n\nOFMAP SRAM Access Count: 1000\n\nIFMAP DRAM Access Count: 13200\n\nFilter DRAM Access Count: 21120\n\nOFMAP DRAM Access Count: 1000\n\nIFMAP Buffer Size (bytes): 6291456\n\nFilter Buffer Size (bytes): 6291456\n\nOFMAP Buffer Size (bytes): 2097152\n\nIFMAP Buffer Utilization (%): 0.209808349609375\n\nFilter Buffer Utilization (%): 0.335693359375\n\nOFMAP Buffer Utilization (%): 0.0476837158203125\n",
    "PE_0004_0001": "Layer ID: 40\n\nGrid Row ID: 4\n\nGrid Col ID: 1\n\nCompute Cycles: 37379.0\n\nIFMAP DRAM Reads: 13200.0\n\nFilter DRAM Reads: 21120.0\n\nOFMAP DRAM Writes: 1000.0\n\nIFMAP DRAM Start Cycle: -15729.0\n\nFilter DRAM Start Cycle: -15729.0\n\nOFMAP DRAM Start Cycle: 37379.0\n\nIFMAP DRAM End Cycle: -1.0\n\nFilter DRAM End Cycle: -1.0\n\nOFMAP DRAM End Cycle: 37628.0\n\nTotal Compute Cycles: 37379\n\nTotal Stall Cycles: 0\n\nIFMAP SRAM Access Range: (1.0, 37374.0)\n\nFilter SRAM Access Range: (1.0, 37377.0)\n\nOFMAP SRAM Access Range: (527.0, 37379.0)\n\nIFMAP DRAM Access Range: (-15729.0, -1.0)\n\nFilter DRAM Access Range: (-15729.0, -1.0)\n\nOFMAP DRAM Access Range: (37379.0, 37628.0)\n\nIFMAP SRAM Access Count: 13200\n\nFilter SRAM Access Count: 21120\n\nOFMAP SRAM Access Count: 1000\n\nIFMAP DRAM Access Count: 13200\n\nFilter DRAM Access Count: 21120\n\nOFMAP DRAM Access Count: 1000\n\nIFMAP Buffer Size (bytes): 6291456\n\nFilter Buffer Size (bytes): 6291456\n\nOFMAP Buffer Size (bytes): 2097152\n\nIFMAP Buffer Utilization (%): 0.209808349609375\n\nFilter Buffer Utilization (%): 0.335693359375\n\nOFMAP Buffer Utilization (%): 0.0476837158203125\n",
    "PE_0004_0002": "Layer ID: 40\n\nGrid Row ID: 4\n\nGrid Col ID: 2\n\nCompute Cycles: 37379.0\n\nIFMAP DRAM Reads: 13200.0\n\nFilter DRAM Reads: 21120.0\n\nOFMAP DRAM Writes: 1000.0\n\nIFMAP DRAM Start Cycle: -15729.0\n\nFilter DRAM Start Cycle: -15729.0\n\nOFMAP DRAM Start Cycle: 37379.0\n\nIFMAP DRAM End Cycle: -1.0\n\nFilter DRAM End Cycle: -1.0\n\nOFMAP DRAM End Cycle: 37628.0\n\nTotal Compute Cycles: 37379\n\nTotal Stall Cycles: 0\n\nIFMAP SRAM Access Range: (1.0, 37374.0)\n\nFilter SRAM Access Range: (1.0, 37377.0)\n\nOFMAP SRAM Access Range: (527.0, 37379.0)\n\nIFMAP DRAM Access Range: (-15729.0, -1.0)\n\nFilter DRAM Access Range: (-15729.0, -1.0)\n\nOFMAP DRAM Access Range: (37379.0, 37628.0)\n\nIFMAP SRAM Access Count: 13200\n\nFilter SRAM Access Count: 21120\n\nOFMAP SRAM Access Count: 1000\n\nIFMAP DRAM Access Count: 13200\n\nFilter DRAM Access Count: 21120\n\nOFMAP DRAM Access Count: 1000\n\nIFMAP Buffer Size (bytes): 6291456\n\nFilter Buffer Size (bytes): 6291456\n\nOFMAP Buffer Size (bytes): 2097152\n\nIFMAP Buffer Utilization (%): 0.209808349609375\n\nFilter Buffer Utilization (%): 0.335693359375\n\nOFMAP Buffer Utilization (%): 0.0476837158203125\n",
    "PE_0004_0003": "Layer ID: 40\n\nGrid Row ID: 4\n\nGrid Col ID: 3\n\nCompute Cycles: 37379.0\n\nIFMAP DRAM Reads: 13200.0\n\nFilter DRAM Reads: 20592.0\n\nOFMAP DRAM Writes: 975.0\n\nIFMAP DRAM Start Cycle: -15729.0\n\nFilter DRAM Start Cycle: -15729.0\n\nOFMAP DRAM Start Cycle: 37379.0\n\nIFMAP DRAM End Cycle: -1.0\n\nFilter DRAM End Cycle: -1.0\n\nOFMAP DRAM End Cycle: 37622.0\n\nTotal Compute Cycles: 37379\n\nTotal Stall Cycles: 0\n\nIFMAP SRAM Access Range: (1.0, 37374.0)\n\nFilter SRAM Access Range: (1.0, 37376.0)\n\nOFMAP SRAM Access Range: (527.0, 37378.0)\n\nIFMAP DRAM Access Range: (-15729.0, -1.0)\n\nFilter DRAM Access Range: (-15729.0, -1.0)\n\nOFMAP DRAM Access Range: (37379.0, 37622.0)\n\nIFMAP SRAM Access Count: 13200\n\nFilter SRAM Access Count: 20592\n\nOFMAP SRAM Access Count: 975\n\nIFMAP DRAM Access Count: 13200\n\nFilter DRAM Access Count: 20592\n\nOFMAP DRAM Access Count: 975\n\nIFMAP Buffer Size (bytes): 6291456\n\nFilter Buffer Size (bytes): 6291456\n\nOFMAP Buffer Size (bytes): 2097152\n\nIFMAP Buffer Utilization (%): 0.209808349609375\n\nFilter Buffer Utilization (%): 0.327301025390625\n\nOFMAP Buffer Utilization (%): 0.04649162292480469\n",
    "PE_0005_0000": "Layer ID: 40\n\nGrid Row ID: 5\n\nGrid Col ID: 0\n\nCompute Cycles: 37379.0\n\nIFMAP DRAM Reads: 13200.0\n\nFilter DRAM Reads: 21120.0\n\nOFMAP DRAM Writes: 1000.0\n\nIFMAP DRAM Start Cycle: -15729.0\n\nFilter DRAM Start Cycle: -15729.0\n\nOFMAP DRAM Start Cycle: 37379.0\n\nIFMAP DRAM End Cycle: -1.0\n\nFilter DRAM End Cycle: -1.0\n\nOFMAP DRAM End Cycle: 37628.0\n\nTotal Compute Cycles: 37379\n\nTotal Stall Cycles: 0\n\nIFMAP SRAM Access Range: (1.0, 37374.0)\n\nFilter SRAM Access Range: (1.0, 37377.0)\n\nOFMAP SRAM Access Range: (527.0, 37379.0)\n\nIFMAP DRAM Access Range: (-15729.0, -1.0)\n\nFilter DRAM Access Range: (-15729.0, -1.0)\n\nOFMAP DRAM Access Range: (37379.0, 37628.0)\n\nIFMAP SRAM Access Count: 13200\n\nFilter SRAM Access Count: 21120\n\nOFMAP SRAM Access Count: 1000\n\nIFMAP DRAM Access Count: 13200\n\nFilter DRAM Access Count: 21120\n\nOFMAP DRAM Access Count: 1000\n\nIFMAP Buffer Size (bytes): 6291456\n\nFilter Buffer Size (bytes): 6291456\n\nOFMAP Buffer Size (bytes): 2097152\n\nIFMAP Buffer Utilization (%): 0.209808349609375\n\nFilter Buffer Utilization (%): 0.335693359375\n\nOFMAP Buffer Utilization (%): 0.0476837158203125\n",
    "PE_0005_0001": "Layer ID: 40\n\nGrid Row ID: 5\n\nGrid Col ID: 1\n\nCompute Cycles: 37379.0\n\nIFMAP DRAM Reads: 13200.0\n\nFilter DRAM Reads: 21120.0\n\nOFMAP DRAM Writes: 1000.0\n\nIFMAP DRAM Start Cycle: -15729.0\n\nFilter DRAM Start Cycle: -15729.0\n\nOFMAP DRAM Start Cycle: 37379.0\n\nIFMAP DRAM End Cycle: -1.0\n\nFilter DRAM End Cycle: -1.0\n\nOFMAP DRAM End Cycle: 37628.0\n\nTotal Compute Cycles: 37379\n\nTotal Stall Cycles: 0\n\nIFMAP SRAM Access Range: (1.0, 37374.0)\n\nFilter SRAM Access Range: (1.0, 37377.0)\n\nOFMAP SRAM Access Range: (527.0, 37379.0)\n\nIFMAP DRAM Access Range: (-15729.0, -1.0)\n\nFilter DRAM Access Range: (-15729.0, -1.0)\n\nOFMAP DRAM Access Range: (37379.0, 37628.0)\n\nIFMAP SRAM Access Count: 13200\n\nFilter SRAM Access Count: 21120\n\nOFMAP SRAM Access Count: 1000\n\nIFMAP DRAM Access Count: 13200\n\nFilter DRAM Access Count: 21120\n\nOFMAP DRAM Access Count: 1000\n\nIFMAP Buffer Size (bytes): 6291456\n\nFilter Buffer Size (bytes): 6291456\n\nOFMAP Buffer Size (bytes): 2097152\n\nIFMAP Buffer Utilization (%): 0.209808349609375\n\nFilter Buffer Utilization (%): 0.335693359375\n\nOFMAP Buffer Utilization (%): 0.0476837158203125\n",
    "PE_0005_0002": "Layer ID: 40\n\nGrid Row ID: 5\n\nGrid Col ID: 2\n\nCompute Cycles: 37379.0\n\nIFMAP DRAM Reads: 13200.0\n\nFilter DRAM Reads: 21120.0\n\nOFMAP DRAM Writes: 1000.0\n\nIFMAP DRAM Start Cycle: -15729.0\n\nFilter DRAM Start Cycle: -15729.0\n\nOFMAP DRAM Start Cycle: 37379.0\n\nIFMAP DRAM End Cycle: -1.0\n\nFilter DRAM End Cycle: -1.0\n\nOFMAP DRAM End Cycle: 37628.0\n\nTotal Compute Cycles: 37379\n\nTotal Stall Cycles: 0\n\nIFMAP SRAM Access Range: (1.0, 37374.0)\n\nFilter SRAM Access Range: (1.0, 37377.0)\n\nOFMAP SRAM Access Range: (527.0, 37379.0)\n\nIFMAP DRAM Access Range: (-15729.0, -1.0)\n\nFilter DRAM Access Range: (-15729.0, -1.0)\n\nOFMAP DRAM Access Range: (37379.0, 37628.0)\n\nIFMAP SRAM Access Count: 13200\n\nFilter SRAM Access Count: 21120\n\nOFMAP SRAM Access Count: 1000\n\nIFMAP DRAM Access Count: 13200\n\nFilter DRAM Access Count: 21120\n\nOFMAP DRAM Access Count: 1000\n\nIFMAP Buffer Size (bytes): 6291456\n\nFilter Buffer Size (bytes): 6291456\n\nOFMAP Buffer Size (bytes): 2097152\n\nIFMAP Buffer Utilization (%): 0.209808349609375\n\nFilter Buffer Utilization (%): 0.335693359375\n\nOFMAP Buffer Utilization (%): 0.0476837158203125\n",
    "PE_0005_0003": "Layer ID: 40\n\nGrid Row ID: 5\n\nGrid Col ID: 3\n\nCompute Cycles: 37379.0\n\nIFMAP DRAM Reads: 13200.0\n\nFilter DRAM Reads: 20592.0\n\nOFMAP DRAM Writes: 975.0\n\nIFMAP DRAM Start Cycle: -15729.0\n\nFilter DRAM Start Cycle: -15729.0\n\nOFMAP DRAM Start Cycle: 37379.0\n\nIFMAP DRAM End Cycle: -1.0\n\nFilter DRAM End Cycle: -1.0\n\nOFMAP DRAM End Cycle: 37622.0\n\nTotal Compute Cycles: 37379\n\nTotal Stall Cycles: 0\n\nIFMAP SRAM Access Range: (1.0, 37374.0)\n\nFilter SRAM Access Range: (1.0, 37376.0)\n\nOFMAP SRAM Access Range: (527.0, 37378.0)\n\nIFMAP DRAM Access Range: (-15729.0, -1.0)\n\nFilter DRAM Access Range: (-15729.0, -1.0)\n\nOFMAP DRAM Access Range: (37379.0, 37622.0)\n\nIFMAP SRAM Access Count: 13200\n\nFilter SRAM Access Count: 20592\n\nOFMAP SRAM Access Count: 975\n\nIFMAP DRAM Access Count: 13200\n\nFilter DRAM Access Count: 20592\n\nOFMAP DRAM Access Count: 975\n\nIFMAP Buffer Size (bytes): 6291456\n\nFilter Buffer Size (bytes): 6291456\n\nOFMAP Buffer Size (bytes): 2097152\n\nIFMAP Buffer Utilization (%): 0.209808349609375\n\nFilter Buffer Utilization (%): 0.327301025390625\n\nOFMAP Buffer Utilization (%): 0.04649162292480469\n",
    "PE_0006_0000": "Layer ID: 40\n\nGrid Row ID: 6\n\nGrid Col ID: 0\n\nCompute Cycles: 37379.0\n\nIFMAP DRAM Reads: 13200.0\n\nFilter DRAM Reads: 21120.0\n\nOFMAP DRAM Writes: 1000.0\n\nIFMAP DRAM Start Cycle: -15729.0\n\nFilter DRAM Start Cycle: -15729.0\n\nOFMAP DRAM Start Cycle: 37379.0\n\nIFMAP DRAM End Cycle: -1.0\n\nFilter DRAM End Cycle: -1.0\n\nOFMAP DRAM End Cycle: 37628.0\n\nTotal Compute Cycles: 37379\n\nTotal Stall Cycles: 0\n\nIFMAP SRAM Access Range: (1.0, 37374.0)\n\nFilter SRAM Access Range: (1.0, 37377.0)\n\nOFMAP SRAM Access Range: (527.0, 37379.0)\n\nIFMAP DRAM Access Range: (-15729.0, -1.0)\n\nFilter DRAM Access Range: (-15729.0, -1.0)\n\nOFMAP DRAM Access Range: (37379.0, 37628.0)\n\nIFMAP SRAM Access Count: 13200\n\nFilter SRAM Access Count: 21120\n\nOFMAP SRAM Access Count: 1000\n\nIFMAP DRAM Access Count: 13200\n\nFilter DRAM Access Count: 21120\n\nOFMAP DRAM Access Count: 1000\n\nIFMAP Buffer Size (bytes): 6291456\n\nFilter Buffer Size (bytes): 6291456\n\nOFMAP Buffer Size (bytes): 2097152\n\nIFMAP Buffer Utilization (%): 0.209808349609375\n\nFilter Buffer Utilization (%): 0.335693359375\n\nOFMAP Buffer Utilization (%): 0.0476837158203125\n",
    "PE_0006_0001": "Layer ID: 40\n\nGrid Row ID: 6\n\nGrid Col ID: 1\n\nCompute Cycles: 37379.0\n\nIFMAP DRAM Reads: 13200.0\n\nFilter DRAM Reads: 21120.0\n\nOFMAP DRAM Writes: 1000.0\n\nIFMAP DRAM Start Cycle: -15729.0\n\nFilter DRAM Start Cycle: -15729.0\n\nOFMAP DRAM Start Cycle: 37379.0\n\nIFMAP DRAM End Cycle: -1.0\n\nFilter DRAM End Cycle: -1.0\n\nOFMAP DRAM End Cycle: 37628.0\n\nTotal Compute Cycles: 37379\n\nTotal Stall Cycles: 0\n\nIFMAP SRAM Access Range: (1.0, 37374.0)\n\nFilter SRAM Access Range: (1.0, 37377.0)\n\nOFMAP SRAM Access Range: (527.0, 37379.0)\n\nIFMAP DRAM Access Range: (-15729.0, -1.0)\n\nFilter DRAM Access Range: (-15729.0, -1.0)\n\nOFMAP DRAM Access Range: (37379.0, 37628.0)\n\nIFMAP SRAM Access Count: 13200\n\nFilter SRAM Access Count: 21120\n\nOFMAP SRAM Access Count: 1000\n\nIFMAP DRAM Access Count: 13200\n\nFilter DRAM Access Count: 21120\n\nOFMAP DRAM Access Count: 1000\n\nIFMAP Buffer Size (bytes): 6291456\n\nFilter Buffer Size (bytes): 6291456\n\nOFMAP Buffer Size (bytes): 2097152\n\nIFMAP Buffer Utilization (%): 0.209808349609375\n\nFilter Buffer Utilization (%): 0.335693359375\n\nOFMAP Buffer Utilization (%): 0.0476837158203125\n",
    "PE_0006_0002": "Layer ID: 40\n\nGrid Row ID: 6\n\nGrid Col ID: 2\n\nCompute Cycles: 37379.0\n\nIFMAP DRAM Reads: 13200.0\n\nFilter DRAM Reads: 21120.0\n\nOFMAP DRAM Writes: 1000.0\n\nIFMAP DRAM Start Cycle: -15729.0\n\nFilter DRAM Start Cycle: -15729.0\n\nOFMAP DRAM Start Cycle: 37379.0\n\nIFMAP DRAM End Cycle: -1.0\n\nFilter DRAM End Cycle: -1.0\n\nOFMAP DRAM End Cycle: 37628.0\n\nTotal Compute Cycles: 37379\n\nTotal Stall Cycles: 0\n\nIFMAP SRAM Access Range: (1.0, 37374.0)\n\nFilter SRAM Access Range: (1.0, 37377.0)\n\nOFMAP SRAM Access Range: (527.0, 37379.0)\n\nIFMAP DRAM Access Range: (-15729.0, -1.0)\n\nFilter DRAM Access Range: (-15729.0, -1.0)\n\nOFMAP DRAM Access Range: (37379.0, 37628.0)\n\nIFMAP SRAM Access Count: 13200\n\nFilter SRAM Access Count: 21120\n\nOFMAP SRAM Access Count: 1000\n\nIFMAP DRAM Access Count: 13200\n\nFilter DRAM Access Count: 21120\n\nOFMAP DRAM Access Count: 1000\n\nIFMAP Buffer Size (bytes): 6291456\n\nFilter Buffer Size (bytes): 6291456\n\nOFMAP Buffer Size (bytes): 2097152\n\nIFMAP Buffer Utilization (%): 0.209808349609375\n\nFilter Buffer Utilization (%): 0.335693359375\n\nOFMAP Buffer Utilization (%): 0.0476837158203125\n",
    "PE_0006_0003": "Layer ID: 40\n\nGrid Row ID: 6\n\nGrid Col ID: 3\n\nCompute Cycles: 37379.0\n\nIFMAP DRAM Reads: 13200.0\n\nFilter DRAM Reads: 20592.0\n\nOFMAP DRAM Writes: 975.0\n\nIFMAP DRAM Start Cycle: -15729.0\n\nFilter DRAM Start Cycle: -15729.0\n\nOFMAP DRAM Start Cycle: 37379.0\n\nIFMAP DRAM End Cycle: -1.0\n\nFilter DRAM End Cycle: -1.0\n\nOFMAP DRAM End Cycle: 37622.0\n\nTotal Compute Cycles: 37379\n\nTotal Stall Cycles: 0\n\nIFMAP SRAM Access Range: (1.0, 37374.0)\n\nFilter SRAM Access Range: (1.0, 37376.0)\n\nOFMAP SRAM Access Range: (527.0, 37378.0)\n\nIFMAP DRAM Access Range: (-15729.0, -1.0)\n\nFilter DRAM Access Range: (-15729.0, -1.0)\n\nOFMAP DRAM Access Range: (37379.0, 37622.0)\n\nIFMAP SRAM Access Count: 13200\n\nFilter SRAM Access Count: 20592\n\nOFMAP SRAM Access Count: 975\n\nIFMAP DRAM Access Count: 13200\n\nFilter DRAM Access Count: 20592\n\nOFMAP DRAM Access Count: 975\n\nIFMAP Buffer Size (bytes): 6291456\n\nFilter Buffer Size (bytes): 6291456\n\nOFMAP Buffer Size (bytes): 2097152\n\nIFMAP Buffer Utilization (%): 0.209808349609375\n\nFilter Buffer Utilization (%): 0.327301025390625\n\nOFMAP Buffer Utilization (%): 0.04649162292480469\n",
    "PE_0007_0000": "Layer ID: 40\n\nGrid Row ID: 7\n\nGrid Col ID: 0\n\nCompute Cycles: 26699.0\n\nIFMAP DRAM Reads: 10560.0\n\nFilter DRAM Reads: 21120.0\n\nOFMAP DRAM Writes: 800.0\n\nIFMAP DRAM Start Cycle: -15729.0\n\nFilter DRAM Start Cycle: -15729.0\n\nOFMAP DRAM Start Cycle: 26699.0\n\nIFMAP DRAM End Cycle: -1.0\n\nFilter DRAM End Cycle: -1.0\n\nOFMAP DRAM End Cycle: 26898.0\n\nTotal Compute Cycles: 26699\n\nTotal Stall Cycles: 0\n\nIFMAP SRAM Access Range: (1.0, 26697.0)\n\nFilter SRAM Access Range: (1.0, 26697.0)\n\nOFMAP SRAM Access Range: (527.0, 26699.0)\n\nIFMAP DRAM Access Range: (-15729.0, -1.0)\n\nFilter DRAM Access Range: (-15729.0, -1.0)\n\nOFMAP DRAM Access Range: (26699.0, 26898.0)\n\nIFMAP SRAM Access Count: 10560\n\nFilter SRAM Access Count: 21120\n\nOFMAP SRAM Access Count: 800\n\nIFMAP DRAM Access Count: 10560\n\nFilter DRAM Access Count: 21120\n\nOFMAP DRAM Access Count: 800\n\nIFMAP Buffer Size (bytes): 6291456\n\nFilter Buffer Size (bytes): 6291456\n\nOFMAP Buffer Size (bytes): 2097152\n\nIFMAP Buffer Utilization (%): 0.1678466796875\n\nFilter Buffer Utilization (%): 0.335693359375\n\nOFMAP Buffer Utilization (%): 0.03814697265625\n",
    "PE_0007_0001": "Layer ID: 40\n\nGrid Row ID: 7\n\nGrid Col ID: 1\n\nCompute Cycles: 26699.0\n\nIFMAP DRAM Reads: 10560.0\n\nFilter DRAM Reads: 21120.0\n\nOFMAP DRAM Writes: 800.0\n\nIFMAP DRAM Start Cycle: -15729.0\n\nFilter DRAM Start Cycle: -15729.0\n\nOFMAP DRAM Start Cycle: 26699.0\n\nIFMAP DRAM End Cycle: -1.0\n\nFilter DRAM End Cycle: -1.0\n\nOFMAP DRAM End Cycle: 26898.0\n\nTotal Compute Cycles: 26699\n\nTotal Stall Cycles: 0\n\nIFMAP SRAM Access Range: (1.0, 26697.0)\n\nFilter SRAM Access Range: (1.0, 26697.0)\n\nOFMAP SRAM Access Range: (527.0, 26699.0)\n\nIFMAP DRAM Access Range: (-15729.0, -1.0)\n\nFilter DRAM Access Range: (-15729.0, -1.0)\n\nOFMAP DRAM Access Range: (26699.0, 26898.0)\n\nIFMAP SRAM Access Count: 10560\n\nFilter SRAM Access Count: 21120\n\nOFMAP SRAM Access Count: 800\n\nIFMAP DRAM Access Count: 10560\n\nFilter DRAM Access Count: 21120\n\nOFMAP DRAM Access Count: 800\n\nIFMAP Buffer Size (bytes): 6291456\n\nFilter Buffer Size (bytes): 6291456\n\nOFMAP Buffer Size (bytes): 2097152\n\nIFMAP Buffer Utilization (%): 0.1678466796875\n\nFilter Buffer Utilization (%): 0.335693359375\n\nOFMAP Buffer Utilization (%): 0.03814697265625\n",
    "PE_0007_0002": "Layer ID: 40\n\nGrid Row ID: 7\n\nGrid Col ID: 2\n\nCompute Cycles: 26699.0\n\nIFMAP DRAM Reads: 10560.0\n\nFilter DRAM Reads: 21120.0\n\nOFMAP DRAM Writes: 800.0\n\nIFMAP DRAM Start Cycle: -15729.0\n\nFilter DRAM Start Cycle: -15729.0\n\nOFMAP DRAM Start Cycle: 26699.0\n\nIFMAP DRAM End Cycle: -1.0\n\nFilter DRAM End Cycle: -1.0\n\nOFMAP DRAM End Cycle: 26898.0\n\nTotal Compute Cycles: 26699\n\nTotal Stall Cycles: 0\n\nIFMAP SRAM Access Range: (1.0, 26697.0)\n\nFilter SRAM Access Range: (1.0, 26697.0)\n\nOFMAP SRAM Access Range: (527.0, 26699.0)\n\nIFMAP DRAM Access Range: (-15729.0, -1.0)\n\nFilter DRAM Access Range: (-15729.0, -1.0)\n\nOFMAP DRAM Access Range: (26699.0, 26898.0)\n\nIFMAP SRAM Access Count: 10560\n\nFilter SRAM Access Count: 21120\n\nOFMAP SRAM Access Count: 800\n\nIFMAP DRAM Access Count: 10560\n\nFilter DRAM Access Count: 21120\n\nOFMAP DRAM Access Count: 800\n\nIFMAP Buffer Size (bytes): 6291456\n\nFilter Buffer Size (bytes): 6291456\n\nOFMAP Buffer Size (bytes): 2097152\n\nIFMAP Buffer Utilization (%): 0.1678466796875\n\nFilter Buffer Utilization (%): 0.335693359375\n\nOFMAP Buffer Utilization (%): 0.03814697265625\n",
    "PE_0007_0003": "Layer ID: 40\n\nGrid Row ID: 7\n\nGrid Col ID: 3\n\nCompute Cycles: 26699.0\n\nIFMAP DRAM Reads: 10560.0\n\nFilter DRAM Reads: 20592.0\n\nOFMAP DRAM Writes: 780.0\n\nIFMAP DRAM Start Cycle: -15729.0\n\nFilter DRAM Start Cycle: -15729.0\n\nOFMAP DRAM Start Cycle: 26699.0\n\nIFMAP DRAM End Cycle: -1.0\n\nFilter DRAM End Cycle: -1.0\n\nOFMAP DRAM End Cycle: 26893.0\n\nTotal Compute Cycles: 26699\n\nTotal Stall Cycles: 0\n\nIFMAP SRAM Access Range: (1.0, 26697.0)\n\nFilter SRAM Access Range: (1.0, 26696.0)\n\nOFMAP SRAM Access Range: (527.0, 26698.0)\n\nIFMAP DRAM Access Range: (-15729.0, -1.0)\n\nFilter DRAM Access Range: (-15729.0, -1.0)\n\nOFMAP DRAM Access Range: (26699.0, 26893.0)\n\nIFMAP SRAM Access Count: 10560\n\nFilter SRAM Access Count: 20592\n\nOFMAP SRAM Access Count: 780\n\nIFMAP DRAM Access Count: 10560\n\nFilter DRAM Access Count: 20592\n\nOFMAP DRAM Access Count: 780\n\nIFMAP Buffer Size (bytes): 6291456\n\nFilter Buffer Size (bytes): 6291456\n\nOFMAP Buffer Size (bytes): 2097152\n\nIFMAP Buffer Utilization (%): 0.1678466796875\n\nFilter Buffer Utilization (%): 0.327301025390625\n\nOFMAP Buffer Utilization (%): 0.03719329833984375\n"
}