{
    "PE_0000_0000": "Layer ID: 6\n\nGrid Row ID: 0\n\nGrid Col ID: 0\n\nCompute Cycles: 420223.0\n\nIFMAP DRAM Reads: 200704.0\n\nFilter DRAM Reads: 4096.0\n\nOFMAP DRAM Writes: 50176.0\n\nIFMAP DRAM Start Cycle: -62914.0\n\nFilter DRAM Start Cycle: -15729.0\n\nOFMAP DRAM Start Cycle: 420223.0\n\nIFMAP DRAM End Cycle: -1.0\n\nFilter DRAM End Cycle: -1.0\n\nOFMAP DRAM End Cycle: 432766.0\n\nTotal Compute Cycles: 420223\n\nTotal Stall Cycles: 0\n\nIFMAP SRAM Access Range: (1.0, 420221.0)\n\nFilter SRAM Access Range: (1.0, 420221.0)\n\nOFMAP SRAM Access Range: (127.0, 420223.0)\n\nIFMAP DRAM Access Range: (-62914.0, -1.0)\n\nFilter DRAM Access Range: (-15729.0, -1.0)\n\nOFMAP DRAM Access Range: (420223.0, 432766.0)\n\nIFMAP SRAM Access Count: 200704\n\nFilter SRAM Access Count: 4096\n\nOFMAP SRAM Access Count: 50176\n\nIFMAP DRAM Access Count: 200704\n\nFilter DRAM Access Count: 4096\n\nOFMAP DRAM Access Count: 50176\n\nIFMAP Buffer Size (bytes): 6291456\n\nFilter Buffer Size (bytes): 6291456\n\nOFMAP Buffer Size (bytes): 2097152\n\nIFMAP Buffer Utilization (%): 3.1901041666666665\n\nFilter Buffer Utilization (%): 0.06510416666666666\n\nOFMAP Buffer Utilization (%): 2.392578125\n",
    "PE_0000_0001": "Layer ID: 6\n\nGrid Row ID: 0\n\nGrid Col ID: 1\n\nCompute Cycles: 420223.0\n\nIFMAP DRAM Reads: 200704.0\n\nFilter DRAM Reads: 4096.0\n\nOFMAP DRAM Writes: 50176.0\n\nIFMAP DRAM Start Cycle: -62914.0\n\nFilter DRAM Start Cycle: -15729.0\n\nOFMAP DRAM Start Cycle: 420223.0\n\nIFMAP DRAM End Cycle: -1.0\n\nFilter DRAM End Cycle: -1.0\n\nOFMAP DRAM End Cycle: 432766.0\n\nTotal Compute Cycles: 420223\n\nTotal Stall Cycles: 0\n\nIFMAP SRAM Access Range: (1.0, 420221.0)\n\nFilter SRAM Access Range: (1.0, 420221.0)\n\nOFMAP SRAM Access Range: (127.0, 420223.0)\n\nIFMAP DRAM Access Range: (-62914.0, -1.0)\n\nFilter DRAM Access Range: (-15729.0, -1.0)\n\nOFMAP DRAM Access Range: (420223.0, 432766.0)\n\nIFMAP SRAM Access Count: 200704\n\nFilter SRAM Access Count: 4096\n\nOFMAP SRAM Access Count: 50176\n\nIFMAP DRAM Access Count: 200704\n\nFilter DRAM Access Count: 4096\n\nOFMAP DRAM Access Count: 50176\n\nIFMAP Buffer Size (bytes): 6291456\n\nFilter Buffer Size (bytes): 6291456\n\nOFMAP Buffer Size (bytes): 2097152\n\nIFMAP Buffer Utilization (%): 3.1901041666666665\n\nFilter Buffer Utilization (%): 0.06510416666666666\n\nOFMAP Buffer Utilization (%): 2.392578125\n",
    "PE_0000_0002": "Layer ID: 6\n\nGrid Row ID: 0\n\nGrid Col ID: 2\n\nCompute Cycles: 420223.0\n\nIFMAP DRAM Reads: 200704.0\n\nFilter DRAM Reads: 4096.0\n\nOFMAP DRAM Writes: 50176.0\n\nIFMAP DRAM Start Cycle: -62914.0\n\nFilter DRAM Start Cycle: -15729.0\n\nOFMAP DRAM Start Cycle: 420223.0\n\nIFMAP DRAM End Cycle: -1.0\n\nFilter DRAM End Cycle: -1.0\n\nOFMAP DRAM End Cycle: 432766.0\n\nTotal Compute Cycles: 420223\n\nTotal Stall Cycles: 0\n\nIFMAP SRAM Access Range: (1.0, 420221.0)\n\nFilter SRAM Access Range: (1.0, 420221.0)\n\nOFMAP SRAM Access Range: (127.0, 420223.0)\n\nIFMAP DRAM Access Range: (-62914.0, -1.0)\n\nFilter DRAM Access Range: (-15729.0, -1.0)\n\nOFMAP DRAM Access Range: (420223.0, 432766.0)\n\nIFMAP SRAM Access Count: 200704\n\nFilter SRAM Access Count: 4096\n\nOFMAP SRAM Access Count: 50176\n\nIFMAP DRAM Access Count: 200704\n\nFilter DRAM Access Count: 4096\n\nOFMAP DRAM Access Count: 50176\n\nIFMAP Buffer Size (bytes): 6291456\n\nFilter Buffer Size (bytes): 6291456\n\nOFMAP Buffer Size (bytes): 2097152\n\nIFMAP Buffer Utilization (%): 3.1901041666666665\n\nFilter Buffer Utilization (%): 0.06510416666666666\n\nOFMAP Buffer Utilization (%): 2.392578125\n",
    "PE_0000_0003": "Layer ID: 6\n\nGrid Row ID: 0\n\nGrid Col ID: 3\n\nCompute Cycles: 420223.0\n\nIFMAP DRAM Reads: 200704.0\n\nFilter DRAM Reads: 3968.0\n\nOFMAP DRAM Writes: 48608.0\n\nIFMAP DRAM Start Cycle: -62914.0\n\nFilter DRAM Start Cycle: -15729.0\n\nOFMAP DRAM Start Cycle: 420223.0\n\nIFMAP DRAM End Cycle: -1.0\n\nFilter DRAM End Cycle: -1.0\n\nOFMAP DRAM End Cycle: 432374.0\n\nTotal Compute Cycles: 420223\n\nTotal Stall Cycles: 0\n\nIFMAP SRAM Access Range: (1.0, 420221.0)\n\nFilter SRAM Access Range: (1.0, 420220.0)\n\nOFMAP SRAM Access Range: (127.0, 420222.0)\n\nIFMAP DRAM Access Range: (-62914.0, -1.0)\n\nFilter DRAM Access Range: (-15729.0, -1.0)\n\nOFMAP DRAM Access Range: (420223.0, 432374.0)\n\nIFMAP SRAM Access Count: 200704\n\nFilter SRAM Access Count: 3968\n\nOFMAP SRAM Access Count: 48608\n\nIFMAP DRAM Access Count: 200704\n\nFilter DRAM Access Count: 3968\n\nOFMAP DRAM Access Count: 48608\n\nIFMAP Buffer Size (bytes): 6291456\n\nFilter Buffer Size (bytes): 6291456\n\nOFMAP Buffer Size (bytes): 2097152\n\nIFMAP Buffer Utilization (%): 3.1901041666666665\n\nFilter Buffer Utilization (%): 0.06306966145833334\n\nOFMAP Buffer Utilization (%): 2.31781005859375\n",
    "PE_0001_0000": "Layer ID: 6\n\nGrid Row ID: 1\n\nGrid Col ID: 0\n\nCompute Cycles: 420223.0\n\nIFMAP DRAM Reads: 200576.0\n\nFilter DRAM Reads: 4096.0\n\nOFMAP DRAM Writes: 50144.0\n\nIFMAP DRAM Start Cycle: -62914.0\n\nFilter DRAM Start Cycle: -15729.0\n\nOFMAP DRAM Start Cycle: 420223.0\n\nIFMAP DRAM End Cycle: -1.0\n\nFilter DRAM End Cycle: -1.0\n\nOFMAP DRAM End Cycle: 432758.0\n\nTotal Compute Cycles: 420223\n\nTotal Stall Cycles: 0\n\nIFMAP SRAM Access Range: (1.0, 420220.0)\n\nFilter SRAM Access Range: (1.0, 420221.0)\n\nOFMAP SRAM Access Range: (127.0, 420223.0)\n\nIFMAP DRAM Access Range: (-62914.0, -1.0)\n\nFilter DRAM Access Range: (-15729.0, -1.0)\n\nOFMAP DRAM Access Range: (420223.0, 432758.0)\n\nIFMAP SRAM Access Count: 200576\n\nFilter SRAM Access Count: 4096\n\nOFMAP SRAM Access Count: 50144\n\nIFMAP DRAM Access Count: 200576\n\nFilter DRAM Access Count: 4096\n\nOFMAP DRAM Access Count: 50144\n\nIFMAP Buffer Size (bytes): 6291456\n\nFilter Buffer Size (bytes): 6291456\n\nOFMAP Buffer Size (bytes): 2097152\n\nIFMAP Buffer Utilization (%): 3.1880696614583335\n\nFilter Buffer Utilization (%): 0.06510416666666666\n\nOFMAP Buffer Utilization (%): 2.39105224609375\n",
    "PE_0001_0001": "Layer ID: 6\n\nGrid Row ID: 1\n\nGrid Col ID: 1\n\nCompute Cycles: 420223.0\n\nIFMAP DRAM Reads: 200576.0\n\nFilter DRAM Reads: 4096.0\n\nOFMAP DRAM Writes: 50144.0\n\nIFMAP DRAM Start Cycle: -62914.0\n\nFilter DRAM Start Cycle: -15729.0\n\nOFMAP DRAM Start Cycle: 420223.0\n\nIFMAP DRAM End Cycle: -1.0\n\nFilter DRAM End Cycle: -1.0\n\nOFMAP DRAM End Cycle: 432758.0\n\nTotal Compute Cycles: 420223\n\nTotal Stall Cycles: 0\n\nIFMAP SRAM Access Range: (1.0, 420220.0)\n\nFilter SRAM Access Range: (1.0, 420221.0)\n\nOFMAP SRAM Access Range: (127.0, 420223.0)\n\nIFMAP DRAM Access Range: (-62914.0, -1.0)\n\nFilter DRAM Access Range: (-15729.0, -1.0)\n\nOFMAP DRAM Access Range: (420223.0, 432758.0)\n\nIFMAP SRAM Access Count: 200576\n\nFilter SRAM Access Count: 4096\n\nOFMAP SRAM Access Count: 50144\n\nIFMAP DRAM Access Count: 200576\n\nFilter DRAM Access Count: 4096\n\nOFMAP DRAM Access Count: 50144\n\nIFMAP Buffer Size (bytes): 6291456\n\nFilter Buffer Size (bytes): 6291456\n\nOFMAP Buffer Size (bytes): 2097152\n\nIFMAP Buffer Utilization (%): 3.1880696614583335\n\nFilter Buffer Utilization (%): 0.06510416666666666\n\nOFMAP Buffer Utilization (%): 2.39105224609375\n",
    "PE_0001_0002": "Layer ID: 6\n\nGrid Row ID: 1\n\nGrid Col ID: 2\n\nCompute Cycles: 420223.0\n\nIFMAP DRAM Reads: 200576.0\n\nFilter DRAM Reads: 4096.0\n\nOFMAP DRAM Writes: 50144.0\n\nIFMAP DRAM Start Cycle: -62914.0\n\nFilter DRAM Start Cycle: -15729.0\n\nOFMAP DRAM Start Cycle: 420223.0\n\nIFMAP DRAM End Cycle: -1.0\n\nFilter DRAM End Cycle: -1.0\n\nOFMAP DRAM End Cycle: 432758.0\n\nTotal Compute Cycles: 420223\n\nTotal Stall Cycles: 0\n\nIFMAP SRAM Access Range: (1.0, 420220.0)\n\nFilter SRAM Access Range: (1.0, 420221.0)\n\nOFMAP SRAM Access Range: (127.0, 420223.0)\n\nIFMAP DRAM Access Range: (-62914.0, -1.0)\n\nFilter DRAM Access Range: (-15729.0, -1.0)\n\nOFMAP DRAM Access Range: (420223.0, 432758.0)\n\nIFMAP SRAM Access Count: 200576\n\nFilter SRAM Access Count: 4096\n\nOFMAP SRAM Access Count: 50144\n\nIFMAP DRAM Access Count: 200576\n\nFilter DRAM Access Count: 4096\n\nOFMAP DRAM Access Count: 50144\n\nIFMAP Buffer Size (bytes): 6291456\n\nFilter Buffer Size (bytes): 6291456\n\nOFMAP Buffer Size (bytes): 2097152\n\nIFMAP Buffer Utilization (%): 3.1880696614583335\n\nFilter Buffer Utilization (%): 0.06510416666666666\n\nOFMAP Buffer Utilization (%): 2.39105224609375\n",
    "PE_0001_0003": "Layer ID: 6\n\nGrid Row ID: 1\n\nGrid Col ID: 3\n\nCompute Cycles: 420223.0\n\nIFMAP DRAM Reads: 200576.0\n\nFilter DRAM Reads: 3968.0\n\nOFMAP DRAM Writes: 48577.0\n\nIFMAP DRAM Start Cycle: -62914.0\n\nFilter DRAM Start Cycle: -15729.0\n\nOFMAP DRAM Start Cycle: 420223.0\n\nIFMAP DRAM End Cycle: -1.0\n\nFilter DRAM End Cycle: -1.0\n\nOFMAP DRAM End Cycle: 432367.0\n\nTotal Compute Cycles: 420223\n\nTotal Stall Cycles: 0\n\nIFMAP SRAM Access Range: (1.0, 420220.0)\n\nFilter SRAM Access Range: (1.0, 420220.0)\n\nOFMAP SRAM Access Range: (127.0, 420222.0)\n\nIFMAP DRAM Access Range: (-62914.0, -1.0)\n\nFilter DRAM Access Range: (-15729.0, -1.0)\n\nOFMAP DRAM Access Range: (420223.0, 432367.0)\n\nIFMAP SRAM Access Count: 200576\n\nFilter SRAM Access Count: 3968\n\nOFMAP SRAM Access Count: 48577\n\nIFMAP DRAM Access Count: 200576\n\nFilter DRAM Access Count: 3968\n\nOFMAP DRAM Access Count: 48577\n\nIFMAP Buffer Size (bytes): 6291456\n\nFilter Buffer Size (bytes): 6291456\n\nOFMAP Buffer Size (bytes): 2097152\n\nIFMAP Buffer Utilization (%): 3.1880696614583335\n\nFilter Buffer Utilization (%): 0.06306966145833334\n\nOFMAP Buffer Utilization (%): 2.3163318634033203\n"
}