{
    "PE_0000_0000": "Layer ID: 46\n\nGrid Row ID: 0\n\nGrid Col ID: 0\n\nCompute Cycles: 10759.0\n\nIFMAP DRAM Reads: 3724.0\n\nFilter DRAM Reads: 21280.0\n\nOFMAP DRAM Writes: 280.0\n\nIFMAP DRAM Start Cycle: -15729.0\n\nFilter DRAM Start Cycle: -15729.0\n\nOFMAP DRAM Start Cycle: 10759.0\n\nIFMAP DRAM End Cycle: -1.0\n\nFilter DRAM End Cycle: -1.0\n\nOFMAP DRAM End Cycle: 10828.0\n\nTotal Compute Cycles: 10759\n\nTotal Stall Cycles: 0\n\nIFMAP SRAM Access Range: (1.0, 10756.0)\n\nFilter SRAM Access Range: (1.0, 10757.0)\n\nOFMAP SRAM Access Range: (531.0, 10759.0)\n\nIFMAP DRAM Access Range: (-15729.0, -1.0)\n\nFilter DRAM Access Range: (-15729.0, -1.0)\n\nOFMAP DRAM Access Range: (10759.0, 10828.0)\n\nIFMAP SRAM Access Count: 3724\n\nFilter SRAM Access Count: 21280\n\nOFMAP SRAM Access Count: 280\n\nIFMAP DRAM Access Count: 3724\n\nFilter DRAM Access Count: 21280\n\nOFMAP DRAM Access Count: 280\n\nIFMAP Buffer Size (bytes): 6291456\n\nFilter Buffer Size (bytes): 6291456\n\nOFMAP Buffer Size (bytes): 2097152\n\nIFMAP Buffer Utilization (%): 0.059191385904947914\n\nFilter Buffer Utilization (%): 0.33823649088541663\n\nOFMAP Buffer Utilization (%): 0.0133514404296875\n",
    "PE_0000_0001": "Layer ID: 46\n\nGrid Row ID: 0\n\nGrid Col ID: 1\n\nCompute Cycles: 10759.0\n\nIFMAP DRAM Reads: 3724.0\n\nFilter DRAM Reads: 21280.0\n\nOFMAP DRAM Writes: 280.0\n\nIFMAP DRAM Start Cycle: -15729.0\n\nFilter DRAM Start Cycle: -15729.0\n\nOFMAP DRAM Start Cycle: 10759.0\n\nIFMAP DRAM End Cycle: -1.0\n\nFilter DRAM End Cycle: -1.0\n\nOFMAP DRAM End Cycle: 10828.0\n\nTotal Compute Cycles: 10759\n\nTotal Stall Cycles: 0\n\nIFMAP SRAM Access Range: (1.0, 10756.0)\n\nFilter SRAM Access Range: (1.0, 10757.0)\n\nOFMAP SRAM Access Range: (531.0, 10759.0)\n\nIFMAP DRAM Access Range: (-15729.0, -1.0)\n\nFilter DRAM Access Range: (-15729.0, -1.0)\n\nOFMAP DRAM Access Range: (10759.0, 10828.0)\n\nIFMAP SRAM Access Count: 3724\n\nFilter SRAM Access Count: 21280\n\nOFMAP SRAM Access Count: 280\n\nIFMAP DRAM Access Count: 3724\n\nFilter DRAM Access Count: 21280\n\nOFMAP DRAM Access Count: 280\n\nIFMAP Buffer Size (bytes): 6291456\n\nFilter Buffer Size (bytes): 6291456\n\nOFMAP Buffer Size (bytes): 2097152\n\nIFMAP Buffer Utilization (%): 0.059191385904947914\n\nFilter Buffer Utilization (%): 0.33823649088541663\n\nOFMAP Buffer Utilization (%): 0.0133514404296875\n",
    "PE_0000_0002": "Layer ID: 46\n\nGrid Row ID: 0\n\nGrid Col ID: 2\n\nCompute Cycles: 10759.0\n\nIFMAP DRAM Reads: 3724.0\n\nFilter DRAM Reads: 21280.0\n\nOFMAP DRAM Writes: 280.0\n\nIFMAP DRAM Start Cycle: -15729.0\n\nFilter DRAM Start Cycle: -15729.0\n\nOFMAP DRAM Start Cycle: 10759.0\n\nIFMAP DRAM End Cycle: -1.0\n\nFilter DRAM End Cycle: -1.0\n\nOFMAP DRAM End Cycle: 10828.0\n\nTotal Compute Cycles: 10759\n\nTotal Stall Cycles: 0\n\nIFMAP SRAM Access Range: (1.0, 10756.0)\n\nFilter SRAM Access Range: (1.0, 10757.0)\n\nOFMAP SRAM Access Range: (531.0, 10759.0)\n\nIFMAP DRAM Access Range: (-15729.0, -1.0)\n\nFilter DRAM Access Range: (-15729.0, -1.0)\n\nOFMAP DRAM Access Range: (10759.0, 10828.0)\n\nIFMAP SRAM Access Count: 3724\n\nFilter SRAM Access Count: 21280\n\nOFMAP SRAM Access Count: 280\n\nIFMAP DRAM Access Count: 3724\n\nFilter DRAM Access Count: 21280\n\nOFMAP DRAM Access Count: 280\n\nIFMAP Buffer Size (bytes): 6291456\n\nFilter Buffer Size (bytes): 6291456\n\nOFMAP Buffer Size (bytes): 2097152\n\nIFMAP Buffer Utilization (%): 0.059191385904947914\n\nFilter Buffer Utilization (%): 0.33823649088541663\n\nOFMAP Buffer Utilization (%): 0.0133514404296875\n",
    "PE_0000_0003": "Layer ID: 46\n\nGrid Row ID: 0\n\nGrid Col ID: 3\n\nCompute Cycles: 10759.0\n\nIFMAP DRAM Reads: 3724.0\n\nFilter DRAM Reads: 20748.0\n\nOFMAP DRAM Writes: 273.0\n\nIFMAP DRAM Start Cycle: -15729.0\n\nFilter DRAM Start Cycle: -15729.0\n\nOFMAP DRAM Start Cycle: 10759.0\n\nIFMAP DRAM End Cycle: -1.0\n\nFilter DRAM End Cycle: -1.0\n\nOFMAP DRAM End Cycle: 10827.0\n\nTotal Compute Cycles: 10759\n\nTotal Stall Cycles: 0\n\nIFMAP SRAM Access Range: (1.0, 10756.0)\n\nFilter SRAM Access Range: (1.0, 10756.0)\n\nOFMAP SRAM Access Range: (531.0, 10758.0)\n\nIFMAP DRAM Access Range: (-15729.0, -1.0)\n\nFilter DRAM Access Range: (-15729.0, -1.0)\n\nOFMAP DRAM Access Range: (10759.0, 10827.0)\n\nIFMAP SRAM Access Count: 3724\n\nFilter SRAM Access Count: 20748\n\nOFMAP SRAM Access Count: 273\n\nIFMAP DRAM Access Count: 3724\n\nFilter DRAM Access Count: 20748\n\nOFMAP DRAM Access Count: 273\n\nIFMAP Buffer Size (bytes): 6291456\n\nFilter Buffer Size (bytes): 6291456\n\nOFMAP Buffer Size (bytes): 2097152\n\nIFMAP Buffer Utilization (%): 0.059191385904947914\n\nFilter Buffer Utilization (%): 0.32978057861328125\n\nOFMAP Buffer Utilization (%): 0.013017654418945312\n",
    "PE_0001_0000": "Layer ID: 46\n\nGrid Row ID: 1\n\nGrid Col ID: 0\n\nCompute Cycles: 10759.0\n\nIFMAP DRAM Reads: 3724.0\n\nFilter DRAM Reads: 21280.0\n\nOFMAP DRAM Writes: 280.0\n\nIFMAP DRAM Start Cycle: -15729.0\n\nFilter DRAM Start Cycle: -15729.0\n\nOFMAP DRAM Start Cycle: 10759.0\n\nIFMAP DRAM End Cycle: -1.0\n\nFilter DRAM End Cycle: -1.0\n\nOFMAP DRAM End Cycle: 10828.0\n\nTotal Compute Cycles: 10759\n\nTotal Stall Cycles: 0\n\nIFMAP SRAM Access Range: (1.0, 10756.0)\n\nFilter SRAM Access Range: (1.0, 10757.0)\n\nOFMAP SRAM Access Range: (531.0, 10759.0)\n\nIFMAP DRAM Access Range: (-15729.0, -1.0)\n\nFilter DRAM Access Range: (-15729.0, -1.0)\n\nOFMAP DRAM Access Range: (10759.0, 10828.0)\n\nIFMAP SRAM Access Count: 3724\n\nFilter SRAM Access Count: 21280\n\nOFMAP SRAM Access Count: 280\n\nIFMAP DRAM Access Count: 3724\n\nFilter DRAM Access Count: 21280\n\nOFMAP DRAM Access Count: 280\n\nIFMAP Buffer Size (bytes): 6291456\n\nFilter Buffer Size (bytes): 6291456\n\nOFMAP Buffer Size (bytes): 2097152\n\nIFMAP Buffer Utilization (%): 0.059191385904947914\n\nFilter Buffer Utilization (%): 0.33823649088541663\n\nOFMAP Buffer Utilization (%): 0.0133514404296875\n",
    "PE_0001_0001": "Layer ID: 46\n\nGrid Row ID: 1\n\nGrid Col ID: 1\n\nCompute Cycles: 10759.0\n\nIFMAP DRAM Reads: 3724.0\n\nFilter DRAM Reads: 21280.0\n\nOFMAP DRAM Writes: 280.0\n\nIFMAP DRAM Start Cycle: -15729.0\n\nFilter DRAM Start Cycle: -15729.0\n\nOFMAP DRAM Start Cycle: 10759.0\n\nIFMAP DRAM End Cycle: -1.0\n\nFilter DRAM End Cycle: -1.0\n\nOFMAP DRAM End Cycle: 10828.0\n\nTotal Compute Cycles: 10759\n\nTotal Stall Cycles: 0\n\nIFMAP SRAM Access Range: (1.0, 10756.0)\n\nFilter SRAM Access Range: (1.0, 10757.0)\n\nOFMAP SRAM Access Range: (531.0, 10759.0)\n\nIFMAP DRAM Access Range: (-15729.0, -1.0)\n\nFilter DRAM Access Range: (-15729.0, -1.0)\n\nOFMAP DRAM Access Range: (10759.0, 10828.0)\n\nIFMAP SRAM Access Count: 3724\n\nFilter SRAM Access Count: 21280\n\nOFMAP SRAM Access Count: 280\n\nIFMAP DRAM Access Count: 3724\n\nFilter DRAM Access Count: 21280\n\nOFMAP DRAM Access Count: 280\n\nIFMAP Buffer Size (bytes): 6291456\n\nFilter Buffer Size (bytes): 6291456\n\nOFMAP Buffer Size (bytes): 2097152\n\nIFMAP Buffer Utilization (%): 0.059191385904947914\n\nFilter Buffer Utilization (%): 0.33823649088541663\n\nOFMAP Buffer Utilization (%): 0.0133514404296875\n",
    "PE_0001_0002": "Layer ID: 46\n\nGrid Row ID: 1\n\nGrid Col ID: 2\n\nCompute Cycles: 10759.0\n\nIFMAP DRAM Reads: 3724.0\n\nFilter DRAM Reads: 21280.0\n\nOFMAP DRAM Writes: 280.0\n\nIFMAP DRAM Start Cycle: -15729.0\n\nFilter DRAM Start Cycle: -15729.0\n\nOFMAP DRAM Start Cycle: 10759.0\n\nIFMAP DRAM End Cycle: -1.0\n\nFilter DRAM End Cycle: -1.0\n\nOFMAP DRAM End Cycle: 10828.0\n\nTotal Compute Cycles: 10759\n\nTotal Stall Cycles: 0\n\nIFMAP SRAM Access Range: (1.0, 10756.0)\n\nFilter SRAM Access Range: (1.0, 10757.0)\n\nOFMAP SRAM Access Range: (531.0, 10759.0)\n\nIFMAP DRAM Access Range: (-15729.0, -1.0)\n\nFilter DRAM Access Range: (-15729.0, -1.0)\n\nOFMAP DRAM Access Range: (10759.0, 10828.0)\n\nIFMAP SRAM Access Count: 3724\n\nFilter SRAM Access Count: 21280\n\nOFMAP SRAM Access Count: 280\n\nIFMAP DRAM Access Count: 3724\n\nFilter DRAM Access Count: 21280\n\nOFMAP DRAM Access Count: 280\n\nIFMAP Buffer Size (bytes): 6291456\n\nFilter Buffer Size (bytes): 6291456\n\nOFMAP Buffer Size (bytes): 2097152\n\nIFMAP Buffer Utilization (%): 0.059191385904947914\n\nFilter Buffer Utilization (%): 0.33823649088541663\n\nOFMAP Buffer Utilization (%): 0.0133514404296875\n",
    "PE_0001_0003": "Layer ID: 46\n\nGrid Row ID: 1\n\nGrid Col ID: 3\n\nCompute Cycles: 10759.0\n\nIFMAP DRAM Reads: 3724.0\n\nFilter DRAM Reads: 20748.0\n\nOFMAP DRAM Writes: 273.0\n\nIFMAP DRAM Start Cycle: -15729.0\n\nFilter DRAM Start Cycle: -15729.0\n\nOFMAP DRAM Start Cycle: 10759.0\n\nIFMAP DRAM End Cycle: -1.0\n\nFilter DRAM End Cycle: -1.0\n\nOFMAP DRAM End Cycle: 10827.0\n\nTotal Compute Cycles: 10759\n\nTotal Stall Cycles: 0\n\nIFMAP SRAM Access Range: (1.0, 10756.0)\n\nFilter SRAM Access Range: (1.0, 10756.0)\n\nOFMAP SRAM Access Range: (531.0, 10758.0)\n\nIFMAP DRAM Access Range: (-15729.0, -1.0)\n\nFilter DRAM Access Range: (-15729.0, -1.0)\n\nOFMAP DRAM Access Range: (10759.0, 10827.0)\n\nIFMAP SRAM Access Count: 3724\n\nFilter SRAM Access Count: 20748\n\nOFMAP SRAM Access Count: 273\n\nIFMAP DRAM Access Count: 3724\n\nFilter DRAM Access Count: 20748\n\nOFMAP DRAM Access Count: 273\n\nIFMAP Buffer Size (bytes): 6291456\n\nFilter Buffer Size (bytes): 6291456\n\nOFMAP Buffer Size (bytes): 2097152\n\nIFMAP Buffer Utilization (%): 0.059191385904947914\n\nFilter Buffer Utilization (%): 0.32978057861328125\n\nOFMAP Buffer Utilization (%): 0.013017654418945312\n",
    "PE_0002_0000": "Layer ID: 46\n\nGrid Row ID: 2\n\nGrid Col ID: 0\n\nCompute Cycles: 10759.0\n\nIFMAP DRAM Reads: 3724.0\n\nFilter DRAM Reads: 21280.0\n\nOFMAP DRAM Writes: 280.0\n\nIFMAP DRAM Start Cycle: -15729.0\n\nFilter DRAM Start Cycle: -15729.0\n\nOFMAP DRAM Start Cycle: 10759.0\n\nIFMAP DRAM End Cycle: -1.0\n\nFilter DRAM End Cycle: -1.0\n\nOFMAP DRAM End Cycle: 10828.0\n\nTotal Compute Cycles: 10759\n\nTotal Stall Cycles: 0\n\nIFMAP SRAM Access Range: (1.0, 10756.0)\n\nFilter SRAM Access Range: (1.0, 10757.0)\n\nOFMAP SRAM Access Range: (531.0, 10759.0)\n\nIFMAP DRAM Access Range: (-15729.0, -1.0)\n\nFilter DRAM Access Range: (-15729.0, -1.0)\n\nOFMAP DRAM Access Range: (10759.0, 10828.0)\n\nIFMAP SRAM Access Count: 3724\n\nFilter SRAM Access Count: 21280\n\nOFMAP SRAM Access Count: 280\n\nIFMAP DRAM Access Count: 3724\n\nFilter DRAM Access Count: 21280\n\nOFMAP DRAM Access Count: 280\n\nIFMAP Buffer Size (bytes): 6291456\n\nFilter Buffer Size (bytes): 6291456\n\nOFMAP Buffer Size (bytes): 2097152\n\nIFMAP Buffer Utilization (%): 0.059191385904947914\n\nFilter Buffer Utilization (%): 0.33823649088541663\n\nOFMAP Buffer Utilization (%): 0.0133514404296875\n",
    "PE_0002_0001": "Layer ID: 46\n\nGrid Row ID: 2\n\nGrid Col ID: 1\n\nCompute Cycles: 10759.0\n\nIFMAP DRAM Reads: 3724.0\n\nFilter DRAM Reads: 21280.0\n\nOFMAP DRAM Writes: 280.0\n\nIFMAP DRAM Start Cycle: -15729.0\n\nFilter DRAM Start Cycle: -15729.0\n\nOFMAP DRAM Start Cycle: 10759.0\n\nIFMAP DRAM End Cycle: -1.0\n\nFilter DRAM End Cycle: -1.0\n\nOFMAP DRAM End Cycle: 10828.0\n\nTotal Compute Cycles: 10759\n\nTotal Stall Cycles: 0\n\nIFMAP SRAM Access Range: (1.0, 10756.0)\n\nFilter SRAM Access Range: (1.0, 10757.0)\n\nOFMAP SRAM Access Range: (531.0, 10759.0)\n\nIFMAP DRAM Access Range: (-15729.0, -1.0)\n\nFilter DRAM Access Range: (-15729.0, -1.0)\n\nOFMAP DRAM Access Range: (10759.0, 10828.0)\n\nIFMAP SRAM Access Count: 3724\n\nFilter SRAM Access Count: 21280\n\nOFMAP SRAM Access Count: 280\n\nIFMAP DRAM Access Count: 3724\n\nFilter DRAM Access Count: 21280\n\nOFMAP DRAM Access Count: 280\n\nIFMAP Buffer Size (bytes): 6291456\n\nFilter Buffer Size (bytes): 6291456\n\nOFMAP Buffer Size (bytes): 2097152\n\nIFMAP Buffer Utilization (%): 0.059191385904947914\n\nFilter Buffer Utilization (%): 0.33823649088541663\n\nOFMAP Buffer Utilization (%): 0.0133514404296875\n",
    "PE_0002_0002": "Layer ID: 46\n\nGrid Row ID: 2\n\nGrid Col ID: 2\n\nCompute Cycles: 10759.0\n\nIFMAP DRAM Reads: 3724.0\n\nFilter DRAM Reads: 21280.0\n\nOFMAP DRAM Writes: 280.0\n\nIFMAP DRAM Start Cycle: -15729.0\n\nFilter DRAM Start Cycle: -15729.0\n\nOFMAP DRAM Start Cycle: 10759.0\n\nIFMAP DRAM End Cycle: -1.0\n\nFilter DRAM End Cycle: -1.0\n\nOFMAP DRAM End Cycle: 10828.0\n\nTotal Compute Cycles: 10759\n\nTotal Stall Cycles: 0\n\nIFMAP SRAM Access Range: (1.0, 10756.0)\n\nFilter SRAM Access Range: (1.0, 10757.0)\n\nOFMAP SRAM Access Range: (531.0, 10759.0)\n\nIFMAP DRAM Access Range: (-15729.0, -1.0)\n\nFilter DRAM Access Range: (-15729.0, -1.0)\n\nOFMAP DRAM Access Range: (10759.0, 10828.0)\n\nIFMAP SRAM Access Count: 3724\n\nFilter SRAM Access Count: 21280\n\nOFMAP SRAM Access Count: 280\n\nIFMAP DRAM Access Count: 3724\n\nFilter DRAM Access Count: 21280\n\nOFMAP DRAM Access Count: 280\n\nIFMAP Buffer Size (bytes): 6291456\n\nFilter Buffer Size (bytes): 6291456\n\nOFMAP Buffer Size (bytes): 2097152\n\nIFMAP Buffer Utilization (%): 0.059191385904947914\n\nFilter Buffer Utilization (%): 0.33823649088541663\n\nOFMAP Buffer Utilization (%): 0.0133514404296875\n",
    "PE_0002_0003": "Layer ID: 46\n\nGrid Row ID: 2\n\nGrid Col ID: 3\n\nCompute Cycles: 10759.0\n\nIFMAP DRAM Reads: 3724.0\n\nFilter DRAM Reads: 20748.0\n\nOFMAP DRAM Writes: 273.0\n\nIFMAP DRAM Start Cycle: -15729.0\n\nFilter DRAM Start Cycle: -15729.0\n\nOFMAP DRAM Start Cycle: 10759.0\n\nIFMAP DRAM End Cycle: -1.0\n\nFilter DRAM End Cycle: -1.0\n\nOFMAP DRAM End Cycle: 10827.0\n\nTotal Compute Cycles: 10759\n\nTotal Stall Cycles: 0\n\nIFMAP SRAM Access Range: (1.0, 10756.0)\n\nFilter SRAM Access Range: (1.0, 10756.0)\n\nOFMAP SRAM Access Range: (531.0, 10758.0)\n\nIFMAP DRAM Access Range: (-15729.0, -1.0)\n\nFilter DRAM Access Range: (-15729.0, -1.0)\n\nOFMAP DRAM Access Range: (10759.0, 10827.0)\n\nIFMAP SRAM Access Count: 3724\n\nFilter SRAM Access Count: 20748\n\nOFMAP SRAM Access Count: 273\n\nIFMAP DRAM Access Count: 3724\n\nFilter DRAM Access Count: 20748\n\nOFMAP DRAM Access Count: 273\n\nIFMAP Buffer Size (bytes): 6291456\n\nFilter Buffer Size (bytes): 6291456\n\nOFMAP Buffer Size (bytes): 2097152\n\nIFMAP Buffer Utilization (%): 0.059191385904947914\n\nFilter Buffer Utilization (%): 0.32978057861328125\n\nOFMAP Buffer Utilization (%): 0.013017654418945312\n",
    "PE_0003_0000": "Layer ID: 46\n\nGrid Row ID: 3\n\nGrid Col ID: 0\n\nCompute Cycles: 10759.0\n\nIFMAP DRAM Reads: 3724.0\n\nFilter DRAM Reads: 21280.0\n\nOFMAP DRAM Writes: 280.0\n\nIFMAP DRAM Start Cycle: -15729.0\n\nFilter DRAM Start Cycle: -15729.0\n\nOFMAP DRAM Start Cycle: 10759.0\n\nIFMAP DRAM End Cycle: -1.0\n\nFilter DRAM End Cycle: -1.0\n\nOFMAP DRAM End Cycle: 10828.0\n\nTotal Compute Cycles: 10759\n\nTotal Stall Cycles: 0\n\nIFMAP SRAM Access Range: (1.0, 10756.0)\n\nFilter SRAM Access Range: (1.0, 10757.0)\n\nOFMAP SRAM Access Range: (531.0, 10759.0)\n\nIFMAP DRAM Access Range: (-15729.0, -1.0)\n\nFilter DRAM Access Range: (-15729.0, -1.0)\n\nOFMAP DRAM Access Range: (10759.0, 10828.0)\n\nIFMAP SRAM Access Count: 3724\n\nFilter SRAM Access Count: 21280\n\nOFMAP SRAM Access Count: 280\n\nIFMAP DRAM Access Count: 3724\n\nFilter DRAM Access Count: 21280\n\nOFMAP DRAM Access Count: 280\n\nIFMAP Buffer Size (bytes): 6291456\n\nFilter Buffer Size (bytes): 6291456\n\nOFMAP Buffer Size (bytes): 2097152\n\nIFMAP Buffer Utilization (%): 0.059191385904947914\n\nFilter Buffer Utilization (%): 0.33823649088541663\n\nOFMAP Buffer Utilization (%): 0.0133514404296875\n",
    "PE_0003_0001": "Layer ID: 46\n\nGrid Row ID: 3\n\nGrid Col ID: 1\n\nCompute Cycles: 10759.0\n\nIFMAP DRAM Reads: 3724.0\n\nFilter DRAM Reads: 21280.0\n\nOFMAP DRAM Writes: 280.0\n\nIFMAP DRAM Start Cycle: -15729.0\n\nFilter DRAM Start Cycle: -15729.0\n\nOFMAP DRAM Start Cycle: 10759.0\n\nIFMAP DRAM End Cycle: -1.0\n\nFilter DRAM End Cycle: -1.0\n\nOFMAP DRAM End Cycle: 10828.0\n\nTotal Compute Cycles: 10759\n\nTotal Stall Cycles: 0\n\nIFMAP SRAM Access Range: (1.0, 10756.0)\n\nFilter SRAM Access Range: (1.0, 10757.0)\n\nOFMAP SRAM Access Range: (531.0, 10759.0)\n\nIFMAP DRAM Access Range: (-15729.0, -1.0)\n\nFilter DRAM Access Range: (-15729.0, -1.0)\n\nOFMAP DRAM Access Range: (10759.0, 10828.0)\n\nIFMAP SRAM Access Count: 3724\n\nFilter SRAM Access Count: 21280\n\nOFMAP SRAM Access Count: 280\n\nIFMAP DRAM Access Count: 3724\n\nFilter DRAM Access Count: 21280\n\nOFMAP DRAM Access Count: 280\n\nIFMAP Buffer Size (bytes): 6291456\n\nFilter Buffer Size (bytes): 6291456\n\nOFMAP Buffer Size (bytes): 2097152\n\nIFMAP Buffer Utilization (%): 0.059191385904947914\n\nFilter Buffer Utilization (%): 0.33823649088541663\n\nOFMAP Buffer Utilization (%): 0.0133514404296875\n",
    "PE_0003_0002": "Layer ID: 46\n\nGrid Row ID: 3\n\nGrid Col ID: 2\n\nCompute Cycles: 10759.0\n\nIFMAP DRAM Reads: 3724.0\n\nFilter DRAM Reads: 21280.0\n\nOFMAP DRAM Writes: 280.0\n\nIFMAP DRAM Start Cycle: -15729.0\n\nFilter DRAM Start Cycle: -15729.0\n\nOFMAP DRAM Start Cycle: 10759.0\n\nIFMAP DRAM End Cycle: -1.0\n\nFilter DRAM End Cycle: -1.0\n\nOFMAP DRAM End Cycle: 10828.0\n\nTotal Compute Cycles: 10759\n\nTotal Stall Cycles: 0\n\nIFMAP SRAM Access Range: (1.0, 10756.0)\n\nFilter SRAM Access Range: (1.0, 10757.0)\n\nOFMAP SRAM Access Range: (531.0, 10759.0)\n\nIFMAP DRAM Access Range: (-15729.0, -1.0)\n\nFilter DRAM Access Range: (-15729.0, -1.0)\n\nOFMAP DRAM Access Range: (10759.0, 10828.0)\n\nIFMAP SRAM Access Count: 3724\n\nFilter SRAM Access Count: 21280\n\nOFMAP SRAM Access Count: 280\n\nIFMAP DRAM Access Count: 3724\n\nFilter DRAM Access Count: 21280\n\nOFMAP DRAM Access Count: 280\n\nIFMAP Buffer Size (bytes): 6291456\n\nFilter Buffer Size (bytes): 6291456\n\nOFMAP Buffer Size (bytes): 2097152\n\nIFMAP Buffer Utilization (%): 0.059191385904947914\n\nFilter Buffer Utilization (%): 0.33823649088541663\n\nOFMAP Buffer Utilization (%): 0.0133514404296875\n",
    "PE_0003_0003": "Layer ID: 46\n\nGrid Row ID: 3\n\nGrid Col ID: 3\n\nCompute Cycles: 10759.0\n\nIFMAP DRAM Reads: 3724.0\n\nFilter DRAM Reads: 20748.0\n\nOFMAP DRAM Writes: 273.0\n\nIFMAP DRAM Start Cycle: -15729.0\n\nFilter DRAM Start Cycle: -15729.0\n\nOFMAP DRAM Start Cycle: 10759.0\n\nIFMAP DRAM End Cycle: -1.0\n\nFilter DRAM End Cycle: -1.0\n\nOFMAP DRAM End Cycle: 10827.0\n\nTotal Compute Cycles: 10759\n\nTotal Stall Cycles: 0\n\nIFMAP SRAM Access Range: (1.0, 10756.0)\n\nFilter SRAM Access Range: (1.0, 10756.0)\n\nOFMAP SRAM Access Range: (531.0, 10758.0)\n\nIFMAP DRAM Access Range: (-15729.0, -1.0)\n\nFilter DRAM Access Range: (-15729.0, -1.0)\n\nOFMAP DRAM Access Range: (10759.0, 10827.0)\n\nIFMAP SRAM Access Count: 3724\n\nFilter SRAM Access Count: 20748\n\nOFMAP SRAM Access Count: 273\n\nIFMAP DRAM Access Count: 3724\n\nFilter DRAM Access Count: 20748\n\nOFMAP DRAM Access Count: 273\n\nIFMAP Buffer Size (bytes): 6291456\n\nFilter Buffer Size (bytes): 6291456\n\nOFMAP Buffer Size (bytes): 2097152\n\nIFMAP Buffer Utilization (%): 0.059191385904947914\n\nFilter Buffer Utilization (%): 0.32978057861328125\n\nOFMAP Buffer Utilization (%): 0.013017654418945312\n",
    "PE_0004_0000": "Layer ID: 46\n\nGrid Row ID: 4\n\nGrid Col ID: 0\n\nCompute Cycles: 10759.0\n\nIFMAP DRAM Reads: 3724.0\n\nFilter DRAM Reads: 21280.0\n\nOFMAP DRAM Writes: 280.0\n\nIFMAP DRAM Start Cycle: -15729.0\n\nFilter DRAM Start Cycle: -15729.0\n\nOFMAP DRAM Start Cycle: 10759.0\n\nIFMAP DRAM End Cycle: -1.0\n\nFilter DRAM End Cycle: -1.0\n\nOFMAP DRAM End Cycle: 10828.0\n\nTotal Compute Cycles: 10759\n\nTotal Stall Cycles: 0\n\nIFMAP SRAM Access Range: (1.0, 10756.0)\n\nFilter SRAM Access Range: (1.0, 10757.0)\n\nOFMAP SRAM Access Range: (531.0, 10759.0)\n\nIFMAP DRAM Access Range: (-15729.0, -1.0)\n\nFilter DRAM Access Range: (-15729.0, -1.0)\n\nOFMAP DRAM Access Range: (10759.0, 10828.0)\n\nIFMAP SRAM Access Count: 3724\n\nFilter SRAM Access Count: 21280\n\nOFMAP SRAM Access Count: 280\n\nIFMAP DRAM Access Count: 3724\n\nFilter DRAM Access Count: 21280\n\nOFMAP DRAM Access Count: 280\n\nIFMAP Buffer Size (bytes): 6291456\n\nFilter Buffer Size (bytes): 6291456\n\nOFMAP Buffer Size (bytes): 2097152\n\nIFMAP Buffer Utilization (%): 0.059191385904947914\n\nFilter Buffer Utilization (%): 0.33823649088541663\n\nOFMAP Buffer Utilization (%): 0.0133514404296875\n",
    "PE_0004_0001": "Layer ID: 46\n\nGrid Row ID: 4\n\nGrid Col ID: 1\n\nCompute Cycles: 10759.0\n\nIFMAP DRAM Reads: 3724.0\n\nFilter DRAM Reads: 21280.0\n\nOFMAP DRAM Writes: 280.0\n\nIFMAP DRAM Start Cycle: -15729.0\n\nFilter DRAM Start Cycle: -15729.0\n\nOFMAP DRAM Start Cycle: 10759.0\n\nIFMAP DRAM End Cycle: -1.0\n\nFilter DRAM End Cycle: -1.0\n\nOFMAP DRAM End Cycle: 10828.0\n\nTotal Compute Cycles: 10759\n\nTotal Stall Cycles: 0\n\nIFMAP SRAM Access Range: (1.0, 10756.0)\n\nFilter SRAM Access Range: (1.0, 10757.0)\n\nOFMAP SRAM Access Range: (531.0, 10759.0)\n\nIFMAP DRAM Access Range: (-15729.0, -1.0)\n\nFilter DRAM Access Range: (-15729.0, -1.0)\n\nOFMAP DRAM Access Range: (10759.0, 10828.0)\n\nIFMAP SRAM Access Count: 3724\n\nFilter SRAM Access Count: 21280\n\nOFMAP SRAM Access Count: 280\n\nIFMAP DRAM Access Count: 3724\n\nFilter DRAM Access Count: 21280\n\nOFMAP DRAM Access Count: 280\n\nIFMAP Buffer Size (bytes): 6291456\n\nFilter Buffer Size (bytes): 6291456\n\nOFMAP Buffer Size (bytes): 2097152\n\nIFMAP Buffer Utilization (%): 0.059191385904947914\n\nFilter Buffer Utilization (%): 0.33823649088541663\n\nOFMAP Buffer Utilization (%): 0.0133514404296875\n",
    "PE_0004_0002": "Layer ID: 46\n\nGrid Row ID: 4\n\nGrid Col ID: 2\n\nCompute Cycles: 10759.0\n\nIFMAP DRAM Reads: 3724.0\n\nFilter DRAM Reads: 21280.0\n\nOFMAP DRAM Writes: 280.0\n\nIFMAP DRAM Start Cycle: -15729.0\n\nFilter DRAM Start Cycle: -15729.0\n\nOFMAP DRAM Start Cycle: 10759.0\n\nIFMAP DRAM End Cycle: -1.0\n\nFilter DRAM End Cycle: -1.0\n\nOFMAP DRAM End Cycle: 10828.0\n\nTotal Compute Cycles: 10759\n\nTotal Stall Cycles: 0\n\nIFMAP SRAM Access Range: (1.0, 10756.0)\n\nFilter SRAM Access Range: (1.0, 10757.0)\n\nOFMAP SRAM Access Range: (531.0, 10759.0)\n\nIFMAP DRAM Access Range: (-15729.0, -1.0)\n\nFilter DRAM Access Range: (-15729.0, -1.0)\n\nOFMAP DRAM Access Range: (10759.0, 10828.0)\n\nIFMAP SRAM Access Count: 3724\n\nFilter SRAM Access Count: 21280\n\nOFMAP SRAM Access Count: 280\n\nIFMAP DRAM Access Count: 3724\n\nFilter DRAM Access Count: 21280\n\nOFMAP DRAM Access Count: 280\n\nIFMAP Buffer Size (bytes): 6291456\n\nFilter Buffer Size (bytes): 6291456\n\nOFMAP Buffer Size (bytes): 2097152\n\nIFMAP Buffer Utilization (%): 0.059191385904947914\n\nFilter Buffer Utilization (%): 0.33823649088541663\n\nOFMAP Buffer Utilization (%): 0.0133514404296875\n",
    "PE_0004_0003": "Layer ID: 46\n\nGrid Row ID: 4\n\nGrid Col ID: 3\n\nCompute Cycles: 10759.0\n\nIFMAP DRAM Reads: 3724.0\n\nFilter DRAM Reads: 20748.0\n\nOFMAP DRAM Writes: 273.0\n\nIFMAP DRAM Start Cycle: -15729.0\n\nFilter DRAM Start Cycle: -15729.0\n\nOFMAP DRAM Start Cycle: 10759.0\n\nIFMAP DRAM End Cycle: -1.0\n\nFilter DRAM End Cycle: -1.0\n\nOFMAP DRAM End Cycle: 10827.0\n\nTotal Compute Cycles: 10759\n\nTotal Stall Cycles: 0\n\nIFMAP SRAM Access Range: (1.0, 10756.0)\n\nFilter SRAM Access Range: (1.0, 10756.0)\n\nOFMAP SRAM Access Range: (531.0, 10758.0)\n\nIFMAP DRAM Access Range: (-15729.0, -1.0)\n\nFilter DRAM Access Range: (-15729.0, -1.0)\n\nOFMAP DRAM Access Range: (10759.0, 10827.0)\n\nIFMAP SRAM Access Count: 3724\n\nFilter SRAM Access Count: 20748\n\nOFMAP SRAM Access Count: 273\n\nIFMAP DRAM Access Count: 3724\n\nFilter DRAM Access Count: 20748\n\nOFMAP DRAM Access Count: 273\n\nIFMAP Buffer Size (bytes): 6291456\n\nFilter Buffer Size (bytes): 6291456\n\nOFMAP Buffer Size (bytes): 2097152\n\nIFMAP Buffer Utilization (%): 0.059191385904947914\n\nFilter Buffer Utilization (%): 0.32978057861328125\n\nOFMAP Buffer Utilization (%): 0.013017654418945312\n",
    "PE_0005_0000": "Layer ID: 46\n\nGrid Row ID: 5\n\nGrid Col ID: 0\n\nCompute Cycles: 10759.0\n\nIFMAP DRAM Reads: 3724.0\n\nFilter DRAM Reads: 21280.0\n\nOFMAP DRAM Writes: 280.0\n\nIFMAP DRAM Start Cycle: -15729.0\n\nFilter DRAM Start Cycle: -15729.0\n\nOFMAP DRAM Start Cycle: 10759.0\n\nIFMAP DRAM End Cycle: -1.0\n\nFilter DRAM End Cycle: -1.0\n\nOFMAP DRAM End Cycle: 10828.0\n\nTotal Compute Cycles: 10759\n\nTotal Stall Cycles: 0\n\nIFMAP SRAM Access Range: (1.0, 10756.0)\n\nFilter SRAM Access Range: (1.0, 10757.0)\n\nOFMAP SRAM Access Range: (531.0, 10759.0)\n\nIFMAP DRAM Access Range: (-15729.0, -1.0)\n\nFilter DRAM Access Range: (-15729.0, -1.0)\n\nOFMAP DRAM Access Range: (10759.0, 10828.0)\n\nIFMAP SRAM Access Count: 3724\n\nFilter SRAM Access Count: 21280\n\nOFMAP SRAM Access Count: 280\n\nIFMAP DRAM Access Count: 3724\n\nFilter DRAM Access Count: 21280\n\nOFMAP DRAM Access Count: 280\n\nIFMAP Buffer Size (bytes): 6291456\n\nFilter Buffer Size (bytes): 6291456\n\nOFMAP Buffer Size (bytes): 2097152\n\nIFMAP Buffer Utilization (%): 0.059191385904947914\n\nFilter Buffer Utilization (%): 0.33823649088541663\n\nOFMAP Buffer Utilization (%): 0.0133514404296875\n",
    "PE_0005_0001": "Layer ID: 46\n\nGrid Row ID: 5\n\nGrid Col ID: 1\n\nCompute Cycles: 10759.0\n\nIFMAP DRAM Reads: 3724.0\n\nFilter DRAM Reads: 21280.0\n\nOFMAP DRAM Writes: 280.0\n\nIFMAP DRAM Start Cycle: -15729.0\n\nFilter DRAM Start Cycle: -15729.0\n\nOFMAP DRAM Start Cycle: 10759.0\n\nIFMAP DRAM End Cycle: -1.0\n\nFilter DRAM End Cycle: -1.0\n\nOFMAP DRAM End Cycle: 10828.0\n\nTotal Compute Cycles: 10759\n\nTotal Stall Cycles: 0\n\nIFMAP SRAM Access Range: (1.0, 10756.0)\n\nFilter SRAM Access Range: (1.0, 10757.0)\n\nOFMAP SRAM Access Range: (531.0, 10759.0)\n\nIFMAP DRAM Access Range: (-15729.0, -1.0)\n\nFilter DRAM Access Range: (-15729.0, -1.0)\n\nOFMAP DRAM Access Range: (10759.0, 10828.0)\n\nIFMAP SRAM Access Count: 3724\n\nFilter SRAM Access Count: 21280\n\nOFMAP SRAM Access Count: 280\n\nIFMAP DRAM Access Count: 3724\n\nFilter DRAM Access Count: 21280\n\nOFMAP DRAM Access Count: 280\n\nIFMAP Buffer Size (bytes): 6291456\n\nFilter Buffer Size (bytes): 6291456\n\nOFMAP Buffer Size (bytes): 2097152\n\nIFMAP Buffer Utilization (%): 0.059191385904947914\n\nFilter Buffer Utilization (%): 0.33823649088541663\n\nOFMAP Buffer Utilization (%): 0.0133514404296875\n",
    "PE_0005_0002": "Layer ID: 46\n\nGrid Row ID: 5\n\nGrid Col ID: 2\n\nCompute Cycles: 10759.0\n\nIFMAP DRAM Reads: 3724.0\n\nFilter DRAM Reads: 21280.0\n\nOFMAP DRAM Writes: 280.0\n\nIFMAP DRAM Start Cycle: -15729.0\n\nFilter DRAM Start Cycle: -15729.0\n\nOFMAP DRAM Start Cycle: 10759.0\n\nIFMAP DRAM End Cycle: -1.0\n\nFilter DRAM End Cycle: -1.0\n\nOFMAP DRAM End Cycle: 10828.0\n\nTotal Compute Cycles: 10759\n\nTotal Stall Cycles: 0\n\nIFMAP SRAM Access Range: (1.0, 10756.0)\n\nFilter SRAM Access Range: (1.0, 10757.0)\n\nOFMAP SRAM Access Range: (531.0, 10759.0)\n\nIFMAP DRAM Access Range: (-15729.0, -1.0)\n\nFilter DRAM Access Range: (-15729.0, -1.0)\n\nOFMAP DRAM Access Range: (10759.0, 10828.0)\n\nIFMAP SRAM Access Count: 3724\n\nFilter SRAM Access Count: 21280\n\nOFMAP SRAM Access Count: 280\n\nIFMAP DRAM Access Count: 3724\n\nFilter DRAM Access Count: 21280\n\nOFMAP DRAM Access Count: 280\n\nIFMAP Buffer Size (bytes): 6291456\n\nFilter Buffer Size (bytes): 6291456\n\nOFMAP Buffer Size (bytes): 2097152\n\nIFMAP Buffer Utilization (%): 0.059191385904947914\n\nFilter Buffer Utilization (%): 0.33823649088541663\n\nOFMAP Buffer Utilization (%): 0.0133514404296875\n",
    "PE_0005_0003": "Layer ID: 46\n\nGrid Row ID: 5\n\nGrid Col ID: 3\n\nCompute Cycles: 10759.0\n\nIFMAP DRAM Reads: 3724.0\n\nFilter DRAM Reads: 20748.0\n\nOFMAP DRAM Writes: 273.0\n\nIFMAP DRAM Start Cycle: -15729.0\n\nFilter DRAM Start Cycle: -15729.0\n\nOFMAP DRAM Start Cycle: 10759.0\n\nIFMAP DRAM End Cycle: -1.0\n\nFilter DRAM End Cycle: -1.0\n\nOFMAP DRAM End Cycle: 10827.0\n\nTotal Compute Cycles: 10759\n\nTotal Stall Cycles: 0\n\nIFMAP SRAM Access Range: (1.0, 10756.0)\n\nFilter SRAM Access Range: (1.0, 10756.0)\n\nOFMAP SRAM Access Range: (531.0, 10758.0)\n\nIFMAP DRAM Access Range: (-15729.0, -1.0)\n\nFilter DRAM Access Range: (-15729.0, -1.0)\n\nOFMAP DRAM Access Range: (10759.0, 10827.0)\n\nIFMAP SRAM Access Count: 3724\n\nFilter SRAM Access Count: 20748\n\nOFMAP SRAM Access Count: 273\n\nIFMAP DRAM Access Count: 3724\n\nFilter DRAM Access Count: 20748\n\nOFMAP DRAM Access Count: 273\n\nIFMAP Buffer Size (bytes): 6291456\n\nFilter Buffer Size (bytes): 6291456\n\nOFMAP Buffer Size (bytes): 2097152\n\nIFMAP Buffer Utilization (%): 0.059191385904947914\n\nFilter Buffer Utilization (%): 0.32978057861328125\n\nOFMAP Buffer Utilization (%): 0.013017654418945312\n",
    "PE_0006_0000": "Layer ID: 46\n\nGrid Row ID: 6\n\nGrid Col ID: 0\n\nCompute Cycles: 10759.0\n\nIFMAP DRAM Reads: 3192.0\n\nFilter DRAM Reads: 21280.0\n\nOFMAP DRAM Writes: 240.0\n\nIFMAP DRAM Start Cycle: -15729.0\n\nFilter DRAM Start Cycle: -15729.0\n\nOFMAP DRAM Start Cycle: 10759.0\n\nIFMAP DRAM End Cycle: -1.0\n\nFilter DRAM End Cycle: -1.0\n\nOFMAP DRAM End Cycle: 10818.0\n\nTotal Compute Cycles: 10759\n\nTotal Stall Cycles: 0\n\nIFMAP SRAM Access Range: (1.0, 10755.0)\n\nFilter SRAM Access Range: (1.0, 10757.0)\n\nOFMAP SRAM Access Range: (531.0, 10759.0)\n\nIFMAP DRAM Access Range: (-15729.0, -1.0)\n\nFilter DRAM Access Range: (-15729.0, -1.0)\n\nOFMAP DRAM Access Range: (10759.0, 10818.0)\n\nIFMAP SRAM Access Count: 3192\n\nFilter SRAM Access Count: 21280\n\nOFMAP SRAM Access Count: 240\n\nIFMAP DRAM Access Count: 3192\n\nFilter DRAM Access Count: 21280\n\nOFMAP DRAM Access Count: 240\n\nIFMAP Buffer Size (bytes): 6291456\n\nFilter Buffer Size (bytes): 6291456\n\nOFMAP Buffer Size (bytes): 2097152\n\nIFMAP Buffer Utilization (%): 0.0507354736328125\n\nFilter Buffer Utilization (%): 0.33823649088541663\n\nOFMAP Buffer Utilization (%): 0.011444091796875\n",
    "PE_0006_0001": "Layer ID: 46\n\nGrid Row ID: 6\n\nGrid Col ID: 1\n\nCompute Cycles: 10759.0\n\nIFMAP DRAM Reads: 3192.0\n\nFilter DRAM Reads: 21280.0\n\nOFMAP DRAM Writes: 240.0\n\nIFMAP DRAM Start Cycle: -15729.0\n\nFilter DRAM Start Cycle: -15729.0\n\nOFMAP DRAM Start Cycle: 10759.0\n\nIFMAP DRAM End Cycle: -1.0\n\nFilter DRAM End Cycle: -1.0\n\nOFMAP DRAM End Cycle: 10818.0\n\nTotal Compute Cycles: 10759\n\nTotal Stall Cycles: 0\n\nIFMAP SRAM Access Range: (1.0, 10755.0)\n\nFilter SRAM Access Range: (1.0, 10757.0)\n\nOFMAP SRAM Access Range: (531.0, 10759.0)\n\nIFMAP DRAM Access Range: (-15729.0, -1.0)\n\nFilter DRAM Access Range: (-15729.0, -1.0)\n\nOFMAP DRAM Access Range: (10759.0, 10818.0)\n\nIFMAP SRAM Access Count: 3192\n\nFilter SRAM Access Count: 21280\n\nOFMAP SRAM Access Count: 240\n\nIFMAP DRAM Access Count: 3192\n\nFilter DRAM Access Count: 21280\n\nOFMAP DRAM Access Count: 240\n\nIFMAP Buffer Size (bytes): 6291456\n\nFilter Buffer Size (bytes): 6291456\n\nOFMAP Buffer Size (bytes): 2097152\n\nIFMAP Buffer Utilization (%): 0.0507354736328125\n\nFilter Buffer Utilization (%): 0.33823649088541663\n\nOFMAP Buffer Utilization (%): 0.011444091796875\n",
    "PE_0006_0002": "Layer ID: 46\n\nGrid Row ID: 6\n\nGrid Col ID: 2\n\nCompute Cycles: 10759.0\n\nIFMAP DRAM Reads: 3192.0\n\nFilter DRAM Reads: 21280.0\n\nOFMAP DRAM Writes: 240.0\n\nIFMAP DRAM Start Cycle: -15729.0\n\nFilter DRAM Start Cycle: -15729.0\n\nOFMAP DRAM Start Cycle: 10759.0\n\nIFMAP DRAM End Cycle: -1.0\n\nFilter DRAM End Cycle: -1.0\n\nOFMAP DRAM End Cycle: 10818.0\n\nTotal Compute Cycles: 10759\n\nTotal Stall Cycles: 0\n\nIFMAP SRAM Access Range: (1.0, 10755.0)\n\nFilter SRAM Access Range: (1.0, 10757.0)\n\nOFMAP SRAM Access Range: (531.0, 10759.0)\n\nIFMAP DRAM Access Range: (-15729.0, -1.0)\n\nFilter DRAM Access Range: (-15729.0, -1.0)\n\nOFMAP DRAM Access Range: (10759.0, 10818.0)\n\nIFMAP SRAM Access Count: 3192\n\nFilter SRAM Access Count: 21280\n\nOFMAP SRAM Access Count: 240\n\nIFMAP DRAM Access Count: 3192\n\nFilter DRAM Access Count: 21280\n\nOFMAP DRAM Access Count: 240\n\nIFMAP Buffer Size (bytes): 6291456\n\nFilter Buffer Size (bytes): 6291456\n\nOFMAP Buffer Size (bytes): 2097152\n\nIFMAP Buffer Utilization (%): 0.0507354736328125\n\nFilter Buffer Utilization (%): 0.33823649088541663\n\nOFMAP Buffer Utilization (%): 0.011444091796875\n",
    "PE_0006_0003": "Layer ID: 46\n\nGrid Row ID: 6\n\nGrid Col ID: 3\n\nCompute Cycles: 10759.0\n\nIFMAP DRAM Reads: 3192.0\n\nFilter DRAM Reads: 20748.0\n\nOFMAP DRAM Writes: 234.0\n\nIFMAP DRAM Start Cycle: -15729.0\n\nFilter DRAM Start Cycle: -15729.0\n\nOFMAP DRAM Start Cycle: 10759.0\n\nIFMAP DRAM End Cycle: -1.0\n\nFilter DRAM End Cycle: -1.0\n\nOFMAP DRAM End Cycle: 10817.0\n\nTotal Compute Cycles: 10759\n\nTotal Stall Cycles: 0\n\nIFMAP SRAM Access Range: (1.0, 10755.0)\n\nFilter SRAM Access Range: (1.0, 10756.0)\n\nOFMAP SRAM Access Range: (531.0, 10758.0)\n\nIFMAP DRAM Access Range: (-15729.0, -1.0)\n\nFilter DRAM Access Range: (-15729.0, -1.0)\n\nOFMAP DRAM Access Range: (10759.0, 10817.0)\n\nIFMAP SRAM Access Count: 3192\n\nFilter SRAM Access Count: 20748\n\nOFMAP SRAM Access Count: 234\n\nIFMAP DRAM Access Count: 3192\n\nFilter DRAM Access Count: 20748\n\nOFMAP DRAM Access Count: 234\n\nIFMAP Buffer Size (bytes): 6291456\n\nFilter Buffer Size (bytes): 6291456\n\nOFMAP Buffer Size (bytes): 2097152\n\nIFMAP Buffer Utilization (%): 0.0507354736328125\n\nFilter Buffer Utilization (%): 0.32978057861328125\n\nOFMAP Buffer Utilization (%): 0.011157989501953125\n",
    "PE_7_0": "An error occurred for PE_7_0",
    "PE_7_1": "An error occurred for PE_7_1",
    "PE_7_2": "An error occurred for PE_7_2",
    "PE_7_3": "An error occurred for PE_7_3"
}